Workbook
Name AS_IS: '[1]Entendimiento de la Iniciativa'!$F$68
Name AS_IS: '[1]Entendimiento de la Iniciativa'!$F$68
Name AS_IS: '[1]Entendimiento de la Iniciativa'!$F$68
Name AS_IS: '[1]Entendimiento de la Iniciativa'!$F$68
Name Calificacion: [2]Catalogo!$A$2:$A$6
Name Estatus: [2]Catalogo!#REF!
Name FolioOP: [3]Carátula!$C$1
Name FolioOP: [3]Carátula!$C$1
Name FolioOP: [3]Carátula!$C$1
Name Frecuencia: [4]Tabla!$A$1:$B$6
Name HorasxDia: [3]Catálogos!$C$2
Name HorasxDia: [3]Catálogos!$C$2
Name HorasxDia: [3]Catálogos!$C$2
Name ListaMVPs: [3]!TblMVPs[MVP]
Name ListaPerfiles: [3]!Tarifario[Perfil de Fábrica E2E]
Name ListaPlataformas: [3]!TblPlataformas[Plataforma]
Name ListaTarifas: [3]!TarifarioHistoria[Fecha]
Name Preguntas: '[1]Entendimiento de la Iniciativa'!$D$13:$D$69
Name Preguntas: '[1]Entendimiento de la Iniciativa'!$D$13:$D$69
Name Preguntas: '[1]Entendimiento de la Iniciativa'!$D$13:$D$69
Name Preguntas: '[1]Entendimiento de la Iniciativa'!$D$13:$D$69
Name Respuestas: '[1]Entendimiento de la Iniciativa'!$F$13:$F$69
Name Respuestas: '[1]Entendimiento de la Iniciativa'!$F$13:$F$69
Name Respuestas: '[1]Entendimiento de la Iniciativa'!$F$13:$F$69
Name Respuestas: '[1]Entendimiento de la Iniciativa'!$F$13:$F$69
Name RiesgoProyecto: [3]Catálogos!$C$6
Name RiesgoProyecto: [3]Catálogos!$C$6
Name RiesgoProyecto: [3]Catálogos!$C$6
Name TarifaColumna: [3]Catálogos!$G$2
Name TarifaColumna: [3]Catálogos!$G$2
Name TarifaColumna: [3]Catálogos!$G$2
Name TarifaSeleccionada: '[3]Plan de trabajo'!$C$7
Name TarifaSeleccionada: '[3]Plan de trabajo'!$C$7
Name TarifaSeleccionada: '[3]Plan de trabajo'!$C$7
Name TO_BE: '[1]Entendimiento de la Iniciativa'!$F$69
Name TO_BE: '[1]Entendimiento de la Iniciativa'!$F$69
Name TO_BE: '[1]Entendimiento de la Iniciativa'!$F$69
Name TO_BE: '[1]Entendimiento de la Iniciativa'!$F$69
Name TotalRiesgo: [3]Estimación!$AM$11
Name TotalRiesgo: [3]Estimación!$AM$11
Name TotalRiesgo: [3]Estimación!$AM$11

Sheet Carátula
C2: Tecnología de Información | F2: Código: Artefacto
C3: Calculadora T-SHIRT 1.3 PAM | F3: Versión 1.3
F4: 45626
F5: Útima Actualización
F6: 45905
B8: Objetivo del documento | D8: Obtener una estimación de alto nivel de la solución a implementar que permita realizar una planeación estratégica desde la perspectiva de negocio apoyando a priorizar las iniciativas por atender.
B9: Dueño de Artefacto | D9: Marlin Mayela Montoya
B10: Versión | C10: Fecha de creación/ actualización | D10: Autor | E10: Comentarios
B11: 1 | C11: 45626 | D11: Yadira Fong Jonathan Chavez Noe Fernando Pérez Arminda Vega Carlos Olivares Marco Vicente Del Valle Malave | E11: Emisión del documento
B12: 1.1 | C12: 45664 | D12: Del Valle Malave Yadira Fong | E12: Cambios en el Cuestionario y estructura de costos de la DOTI
B13: 1.2 | C13: 45812 | D13: Yadira Fong | E13: Se quitan las plataformas de IMA y GEO en el cálculo de la célula, el resultado de estas plataformas se agregan directo a la pestaña de resultados.
B14: 1.3 | C14: 45905 | D14: Del Valle Malave | E14: Se realizan ajustes a los costos Operativos en el cuestionario y la optimización a 2 recursos: SER + Ing de Observabilidad e Ing de Infraestructura. Agrega diagrama de arquitectura Contextual

Sheet Proc de Neg (To-Be)
A2: Folio (OPLATAM) | E2: XX | M2: Product Owner | Q2: Ana Vasquez de Velasco Garay
A3: Nombre de Iniciativa | E3: Recaudo de Servicios con BBVA | M3: TPO | Q3: <Nombre del Technical Product Owner>
A4: Área/Plataforma Solicitante | E4: XX | M4: CS | Q4: <Nombre del Coordinador de Soluciones>
A5: Fecha | E5: 45891 | M5: Arq. Soluciones | Q5: Marco Vicente
K7: Instrucciones
B8: Product Owner el proceso TO BE es importante para ubicar como tu producto estaría impactando a la compañía, en esta sección puedes ir incluyendo los procesos identificados desde la etapa de t-shirt y lo que se vaya agregando referente a tu producto.
B10: <Se deben respaldar los resultados mapa de proceso, journeys, lo que se adjunta es un ejemplo no es necesario que sea BPMN.>

Sheet Epic Backlog
A1: Num Epica | B1: Nombre Epica | C1: Descripción | D1: Criterios de Aceptación | E1: MVP en el que se estima se desarrolle | F1: ¿La Épica tiene dependencia para su desarrollo? | G1: ¿De que Épica depende? | H1: Plataformas Involucradas | O1: Complejidad | T1: Complejidad | U1: Tiempo Estimado (semanas) | V1: Costo | AC1: Costo Estimado
H2: Suite GEO | I2: BO (INT BackOffice) | J2: BO (WEB/WF) | K2: BO (RMS) | L2: BO (EBS) | M2: BO (RDM) | N2: IMA | O2: XL | P2: L | Q2: M | R2: S | S2: XS | V2: Suite GEO | W2: BO (INT BackOffice) | X2: BO (WEB/WF) | Y2: BO (RMS) | Z2: BO (EBS) | AA2: BO (RDM) | AB2: IMA
A3: 1 | B3: Geo- Habilitación de la autopista de servicios | C3: Como negocio, quiero contar con una carretera que integre la recaudación de los servicios desde el punto de venta hasta el EBS. | D3: Debe soportar comisiones fijas, variales, porcentuales, etc que el partner nos indique y debe ser configurables. Contar con la configuración de servicios en la caja de servicios propia de Geo. Replicar la configuración del servicio de manera automática en una tabla customizada que estará alojada en EBS. Debe enviar la información para la contabilización. Debe enviar información de manera diaria a Reportería BI (ODS) Debe generar el archivo de cierre de día. Debe generar el resumen operativo. Registro en la tabla GL_Interface de EBS (Conciliaciones administrativas). | E3: MVP1 | O3: =COUNTIF(I3:N3,O$2) -> 0 | P3: =COUNTIF(I3:N3,P$2) -> 0 | Q3: =COUNTIF(I3:N3,Q$2) -> 0 | R3: =COUNTIF(I3:N3,R$2) -> 0 | S3: =COUNTIF(I3:O3,S$2) -> 0 | T3: =IF(COUNTBLANK(I3:N3)=6,0,IF(O3>0,$O$2,IF(P3>2,$O$2,IF(P3>0,$P$2,IF(Q3>2,$P$2,IF(Q3>0,$Q$2,IF(R3>2,$Q$2,IF(R3>0,$R$2,IF(S3>2,$R$2,$S$2))))))))) -> 0 | U3: =IFERROR(VLOOKUP(T3,$A$27:$B$31,2,0),0) -> 0 | V3: =IFERROR(VLOOKUP(H3,$A$26:$C$31,3,0),0) -> 0 | W3: =IFERROR(VLOOKUP(I3,$A$26:$C$31,3,0),0) -> 0 | X3: =IFERROR(VLOOKUP(J3,$A$26:$C$31,3,0),0) -> 0 | Y3: =IFERROR(VLOOKUP(K3,$A$26:$C$31,3,0),0) -> 0 | Z3: =IFERROR(VLOOKUP(L3,$A$26:$C$31,3,0),0) -> 0 | AA3: =IFERROR(VLOOKUP(M3,$A$26:$C$31,3,0),0) -> 0 | AB3: =IFERROR(VLOOKUP(N3,$A$26:$C$31,3,0),0) -> 0 | AC3: =SUM(V3:AB3) -> 0
A4: 2 | B4: Geo-Recaudo de servicios | C4: Como cajero quiero poder consultar, validar y ejecutar el pago de los servicios desde el portal principal por GeoPos. | D4: Conectarse con el operador del servicio (BBVA). Habilitar los servicios para el cobro mediante los medios de pago respectivo. Cuando ocurra un error de conectividad, debe mostrarse alerta/mensaje al cajero en el POS. Tener la opción de invocar el nombre del servicio que desea pagar (buscador). Contar con un listado de las opciones de los servicios invocados para el servicio a pagar. Seleccionar el servicio que el cliente desea pagar. Permitir ingresar datos asociados al servicio (item del convenio/Recaudo). Mostrar el detalle del servicio a pagar. Permitir generar la simulación de pago para la validación del cliente. Ejecutar de un pago a más de acuerdo a las especificaciones del servicio. No se permite anulaciones después del pago del servicio. | E4: MVP1 | G4: 1 | H4: SI | O4: =COUNTIF(I4:N4,O$2) -> 0 | P4: =COUNTIF(I4:N4,P$2) -> 0 | Q4: =COUNTIF(I4:N4,Q$2) -> 0 | R4: =COUNTIF(I4:N4,R$2) -> 0 | S4: =COUNTIF(I4:O4,S$2) -> 0 | T4: =IF(COUNTBLANK(I4:N4)=6,0,IF(O4>0,$O$2,IF(P4>2,$O$2,IF(P4>0,$P$2,IF(Q4>2,$P$2,IF(Q4>0,$Q$2,IF(R4>2,$Q$2,IF(R4>0,$R$2,IF(S4>2,$R$2,$S$2))))))))) -> 0 | U4: =IFERROR(VLOOKUP(T4,$A$27:$B$31,2,0),0) -> 0 | V4: =IFERROR(VLOOKUP(H4,$A$26:$C$31,3,0),0) -> 0 | W4: =IFERROR(VLOOKUP(I4,$A$26:$C$31,3,0),0) -> 0 | X4: =IFERROR(VLOOKUP(J4,$A$26:$C$31,3,0),0) -> 0 | Y4: =IFERROR(VLOOKUP(K4,$A$26:$C$31,3,0),0) -> 0 | Z4: =IFERROR(VLOOKUP(L4,$A$26:$C$31,3,0),0) -> 0 | AA4: =IFERROR(VLOOKUP(M4,$A$26:$C$31,3,0),0) -> 0 | AB4: =IFERROR(VLOOKUP(N4,$A$26:$C$31,3,0),0) -> 0 | AC4: =SUM(V4:AB4) -> 0
A5: 3 | B5: Geo-Impresión del Documento como sustento de la transacción. | C5: Como negocio, quiero recibir un documento de recaudo propio del servicio, para tener respaldo de la operación realizada en Oxxo. | D5: Se debe generar un documento impreso con los datos de la operación. El documento debe ser legible y con las especificaciones permitidas para cada servicio. El documento debe servir como respaldo válido para un comprobante de pago de servicio La impresión del documento debe ser emitido por duplicado uno para cliente y el otro para el cajero. Los servicios estan exonerados de IGV. El documento nos es un comprobante tributario por lo cual no se debe emitir como factura o boleta de venta, ya que se define como comprobante de recaudo. | E5: MVP1 | G5: 1 | H5: SI | O5: =COUNTIF(I5:N5,O$2) -> 0 | P5: =COUNTIF(I5:N5,P$2) -> 0 | Q5: =COUNTIF(I5:N5,Q$2) -> 0 | R5: =COUNTIF(I5:N5,R$2) -> 0 | S5: =COUNTIF(I5:O5,S$2) -> 0 | T5: =IF(COUNTBLANK(I5:N5)=6,0,IF(O5>0,$O$2,IF(P5>2,$O$2,IF(P5>0,$P$2,IF(Q5>2,$P$2,IF(Q5>0,$Q$2,IF(R5>2,$Q$2,IF(R5>0,$R$2,IF(S5>2,$R$2,$S$2))))))))) -> 0 | U5: =IFERROR(VLOOKUP(T5,$A$27:$B$31,2,0),0) -> 0 | V5: =IFERROR(VLOOKUP(H5,$A$26:$C$31,3,0),0) -> 0 | W5: =IFERROR(VLOOKUP(I5,$A$26:$C$31,3,0),0) -> 0 | X5: =IFERROR(VLOOKUP(J5,$A$26:$C$31,3,0),0) -> 0 | Y5: =IFERROR(VLOOKUP(K5,$A$26:$C$31,3,0),0) -> 0 | Z5: =IFERROR(VLOOKUP(L5,$A$26:$C$31,3,0),0) -> 0 | AA5: =IFERROR(VLOOKUP(M5,$A$26:$C$31,3,0),0) -> 0 | AB5: =IFERROR(VLOOKUP(N5,$A$26:$C$31,3,0),0) -> 0 | AC5: =SUM(V5:AB5) -> 0
A6: 4 | B6: EBS- Creación de tabla customizada | C6: Como negocio, quiero que se cree una tabla customizada y que Geo alimente esta tabla con la información de los servicios. | D6: Debe crearse una tabla customizada en EBS para replicar la información del servicio desde Geo. La tabla debe permitir la alimentación de la información de los servicios de forma automática, enviada desde Geo. Replicar la configuración del servicio en una tabla customizada que estará alojada en EBS. Tabla Custom en EBS Cabecera: RUT Proveedor, Nombre Proveedor, Código ITEM, Descripción, Código Impuesto, Tasa Impuesto, Costo, Precio de Venta, Comisión: Si-No, Tipo Comisión: Fija-Porcentaje, Valor Comisión, Afecta GL: Si-NO, Afecta AP: SI-NO, Afecta AR: SI - NO, Tipo Documento AP: Factura-Nota Crédito, Valor Documento AP: Total-Comisión, Tipo Documento AR: Factura - Nota de Crédito, Valor Documento AR: Total-Comisión, Descripción Asiento, frecuencia de facturación a AR y AP. Tabla Custom en EBS Líneas: Origen: Servicios, Código ITEM, No Línea, Tipo Afectación: Plaza-CR Tienda, Valor a Considerar: Costo-Precio de Venta, Tipo Movimiento: Debito-Crédito, Cuenta, Descripción Línea, frecuencia de facturación a AR y AP. | E6: MVP1 | G6: 2 | O6: =COUNTIF(I6:N6,O$2) -> 0 | P6: =COUNTIF(I6:N6,P$2) -> 0 | Q6: =COUNTIF(I6:N6,Q$2) -> 0 | R6: =COUNTIF(I6:N6,R$2) -> 0 | S6: =COUNTIF(I6:O6,S$2) -> 0 | T6: =IF(COUNTBLANK(I6:N6)=6,0,IF(O6>0,$O$2,IF(P6>2,$O$2,IF(P6>0,$P$2,IF(Q6>2,$P$2,IF(Q6>0,$Q$2,IF(R6>2,$Q$2,IF(R6>0,$R$2,IF(S6>2,$R$2,$S$2))))))))) -> 0 | U6: =IFERROR(VLOOKUP(T6,$A$27:$B$31,2,0),0) -> 0 | V6: =IFERROR(VLOOKUP(H6,$A$26:$C$31,3,0),0) -> 0 | W6: =IFERROR(VLOOKUP(I6,$A$26:$C$31,3,0),0) -> 0 | X6: =IFERROR(VLOOKUP(J6,$A$26:$C$31,3,0),0) -> 0 | Y6: =IFERROR(VLOOKUP(K6,$A$26:$C$31,3,0),0) -> 0 | Z6: =IFERROR(VLOOKUP(L6,$A$26:$C$31,3,0),0) -> 0 | AA6: =IFERROR(VLOOKUP(M6,$A$26:$C$31,3,0),0) -> 0 | AB6: =IFERROR(VLOOKUP(N6,$A$26:$C$31,3,0),0) -> 0 | AC6: =SUM(V6:AB6) -> 0
A7: 5 | B7: EBS-Generación de póliza contable | C7: Como negocio, quiero que se genere la poliza contable de los servicios emitidos para ser expuesta a GL_interface. | D7: El sistema debe generar una cuenta contable por los servicios emitidos. Las cuentas debe ser enviada a la GL_interface para la integración a EBS. La póliza consolidada debe ser por día, tienda y servicio. | E7: MVP1 | G7: 2 | O7: =COUNTIF(I7:N7,O$2) -> 0 | P7: =COUNTIF(I7:N7,P$2) -> 0 | Q7: =COUNTIF(I7:N7,Q$2) -> 0 | R7: =COUNTIF(I7:N7,R$2) -> 0 | S7: =COUNTIF(I7:O7,S$2) -> 0 | T7: =IF(COUNTBLANK(I7:N7)=6,0,IF(O7>0,$O$2,IF(P7>2,$O$2,IF(P7>0,$P$2,IF(Q7>2,$P$2,IF(Q7>0,$Q$2,IF(R7>2,$Q$2,IF(R7>0,$R$2,IF(S7>2,$R$2,$S$2))))))))) -> 0 | U7: =IFERROR(VLOOKUP(T7,$A$27:$B$31,2,0),0) -> 0 | V7: =IFERROR(VLOOKUP(H7,$A$26:$C$31,3,0),0) -> 0 | W7: =IFERROR(VLOOKUP(I7,$A$26:$C$31,3,0),0) -> 0 | X7: =IFERROR(VLOOKUP(J7,$A$26:$C$31,3,0),0) -> 0 | Y7: =IFERROR(VLOOKUP(K7,$A$26:$C$31,3,0),0) -> 0 | Z7: =IFERROR(VLOOKUP(L7,$A$26:$C$31,3,0),0) -> 0 | AA7: =IFERROR(VLOOKUP(M7,$A$26:$C$31,3,0),0) -> 0 | AB7: =IFERROR(VLOOKUP(N7,$A$26:$C$31,3,0),0) -> 0 | AC7: =SUM(V7:AB7) -> 0
A8: 6 | B8: EBS-Automatización de la importación de los servicios | C8: Como negocio, quiero que las polizas que lleguen como servicios se importen y contabilice en automático | D8: El proceso se debe dejar programado para ejecución una vez al día posterior a la hora de generación de importación del punto de venta. | E8: MVP1 | G8: 5 | O8: =COUNTIF(I8:N8,O$2) -> 0 | P8: =COUNTIF(I8:N8,P$2) -> 0 | Q8: =COUNTIF(I8:N8,Q$2) -> 0 | R8: =COUNTIF(I8:N8,R$2) -> 0 | S8: =COUNTIF(I8:O8,S$2) -> 0 | T8: =IF(COUNTBLANK(I8:N8)=6,0,IF(O8>0,$O$2,IF(P8>2,$O$2,IF(P8>0,$P$2,IF(Q8>2,$P$2,IF(Q8>0,$Q$2,IF(R8>2,$Q$2,IF(R8>0,$R$2,IF(S8>2,$R$2,$S$2))))))))) -> 0 | U8: =IFERROR(VLOOKUP(T8,$A$27:$B$31,2,0),0) -> 0 | V8: =IFERROR(VLOOKUP(H8,$A$26:$C$31,3,0),0) -> 0 | W8: =IFERROR(VLOOKUP(I8,$A$26:$C$31,3,0),0) -> 0 | X8: =IFERROR(VLOOKUP(J8,$A$26:$C$31,3,0),0) -> 0 | Y8: =IFERROR(VLOOKUP(K8,$A$26:$C$31,3,0),0) -> 0 | Z8: =IFERROR(VLOOKUP(L8,$A$26:$C$31,3,0),0) -> 0 | AA8: =IFERROR(VLOOKUP(M8,$A$26:$C$31,3,0),0) -> 0 | AB8: =IFERROR(VLOOKUP(N8,$A$26:$C$31,3,0),0) -> 0 | AC8: =SUM(V8:AB8) -> 0
A9: 7 | B9: EBS-Automatización de facturación en modulo de cuentas por pagar | C9: Como negocio, en caso que el servicio debe generar una factura en cuenta por pagar esta debe generarse con la configuración definida en el servicio. (Frecuencia y nivel de consolidación) | D9: La información Se va tomar de la información ya procesada en el módulo de contablidad y con la configuración que tenga validado el servicio | E9: MVP1 | G9: 6 | O9: =COUNTIF(I9:N9,O$2) -> 0 | P9: =COUNTIF(I9:N9,P$2) -> 0 | Q9: =COUNTIF(I9:N9,Q$2) -> 0 | R9: =COUNTIF(I9:N9,R$2) -> 0 | S9: =COUNTIF(I9:O9,S$2) -> 0 | T9: =IF(COUNTBLANK(I9:N9)=6,0,IF(O9>0,$O$2,IF(P9>2,$O$2,IF(P9>0,$P$2,IF(Q9>2,$P$2,IF(Q9>0,$Q$2,IF(R9>2,$Q$2,IF(R9>0,$R$2,IF(S9>2,$R$2,$S$2))))))))) -> 0 | U9: =IFERROR(VLOOKUP(T9,$A$27:$B$31,2,0),0) -> 0 | V9: =IFERROR(VLOOKUP(H9,$A$26:$C$31,3,0),0) -> 0 | W9: =IFERROR(VLOOKUP(I9,$A$26:$C$31,3,0),0) -> 0 | X9: =IFERROR(VLOOKUP(J9,$A$26:$C$31,3,0),0) -> 0 | Y9: =IFERROR(VLOOKUP(K9,$A$26:$C$31,3,0),0) -> 0 | Z9: =IFERROR(VLOOKUP(L9,$A$26:$C$31,3,0),0) -> 0 | AA9: =IFERROR(VLOOKUP(M9,$A$26:$C$31,3,0),0) -> 0 | AB9: =IFERROR(VLOOKUP(N9,$A$26:$C$31,3,0),0) -> 0 | AC9: =SUM(V9:AB9) -> 0
A10: 8 | B10: EBS-Automatización de facturación en modulo de cuentas por cobrar | C10: Como negocio, en caso que el servicio debe generar una factura en cuentas por cobrar esta debe generarse con la configuración definida en el servicio. (Frecuencia y nivel de consolidación) | D10: La información Se va tomar de la información ya procesada en el módulo de contablidad y con la configuración que tenga validado el servicio | E10: MVP1 | G10: 6 | O10: =COUNTIF(I10:N10,O$2) -> 0 | P10: =COUNTIF(I10:N10,P$2) -> 0 | Q10: =COUNTIF(I10:N10,Q$2) -> 0 | R10: =COUNTIF(I10:N10,R$2) -> 0 | S10: =COUNTIF(I10:O10,S$2) -> 0 | T10: =IF(COUNTBLANK(I10:N10)=6,0,IF(O10>0,$O$2,IF(P10>2,$O$2,IF(P10>0,$P$2,IF(Q10>2,$P$2,IF(Q10>0,$Q$2,IF(R10>2,$Q$2,IF(R10>0,$R$2,IF(S10>2,$R$2,$S$2))))))))) -> 0 | U10: =IFERROR(VLOOKUP(T10,$A$27:$B$31,2,0),0) -> 0 | V10: =IFERROR(VLOOKUP(H10,$A$26:$C$31,3,0),0) -> 0 | W10: =IFERROR(VLOOKUP(I10,$A$26:$C$31,3,0),0) -> 0 | X10: =IFERROR(VLOOKUP(J10,$A$26:$C$31,3,0),0) -> 0 | Y10: =IFERROR(VLOOKUP(K10,$A$26:$C$31,3,0),0) -> 0 | Z10: =IFERROR(VLOOKUP(L10,$A$26:$C$31,3,0),0) -> 0 | AA10: =IFERROR(VLOOKUP(M10,$A$26:$C$31,3,0),0) -> 0 | AB10: =IFERROR(VLOOKUP(N10,$A$26:$C$31,3,0),0) -> 0 | AC10: =SUM(V10:AB10) -> 0
A11: 9 | B11: BI- Reportería recaudo de Servicios | C11: Como negocio, quiero contar con la información diaria de los pagos de servicios para las conciliaciones | D11: El reporte debe mostrar la información detallada por cada tipo de servicio. Debe separar la comision que pago el cliente por el recaudo y la comisión pactada entre OXXO y BBVA. Debe mapearse las operaciones que estan afectas y no afectas a IGV | E11: MVP1 | G11: 8 | O11: =COUNTIF(I11:N11,O$2) -> 0 | P11: =COUNTIF(I11:N11,P$2) -> 0 | Q11: =COUNTIF(I11:N11,Q$2) -> 0 | R11: =COUNTIF(I11:N11,R$2) -> 0 | S11: =COUNTIF(I11:O11,S$2) -> 0 | T11: =IF(COUNTBLANK(I11:N11)=6,0,IF(O11>0,$O$2,IF(P11>2,$O$2,IF(P11>0,$P$2,IF(Q11>2,$P$2,IF(Q11>0,$Q$2,IF(R11>2,$Q$2,IF(R11>0,$R$2,IF(S11>2,$R$2,$S$2))))))))) -> 0 | U11: =IFERROR(VLOOKUP(T11,$A$27:$B$31,2,0),0) -> 0 | V11: =IFERROR(VLOOKUP(H11,$A$26:$C$31,3,0),0) -> 0 | W11: =IFERROR(VLOOKUP(I11,$A$26:$C$31,3,0),0) -> 0 | X11: =IFERROR(VLOOKUP(J11,$A$26:$C$31,3,0),0) -> 0 | Y11: =IFERROR(VLOOKUP(K11,$A$26:$C$31,3,0),0) -> 0 | Z11: =IFERROR(VLOOKUP(L11,$A$26:$C$31,3,0),0) -> 0 | AA11: =IFERROR(VLOOKUP(M11,$A$26:$C$31,3,0),0) -> 0 | AB11: =IFERROR(VLOOKUP(N11,$A$26:$C$31,3,0),0) -> 0 | AC11: =SUM(V11:AB11) -> 0
A12: 10 | O12: =COUNTIF(I12:N12,O$2) -> 0 | P12: =COUNTIF(I12:N12,P$2) -> 0 | Q12: =COUNTIF(I12:N12,Q$2) -> 0 | R12: =COUNTIF(I12:N12,R$2) -> 0 | S12: =COUNTIF(I12:O12,S$2) -> 0 | T12: =IF(COUNTBLANK(I12:N12)=6,0,IF(O12>0,$O$2,IF(P12>2,$O$2,IF(P12>0,$P$2,IF(Q12>2,$P$2,IF(Q12>0,$Q$2,IF(R12>2,$Q$2,IF(R12>0,$R$2,IF(S12>2,$R$2,$S$2))))))))) -> 0 | U12: =IFERROR(VLOOKUP(T12,$A$27:$B$31,2,0),0) -> 0 | V12: =IFERROR(VLOOKUP(H12,$A$26:$C$31,3,0),0) -> 0 | W12: =IFERROR(VLOOKUP(I12,$A$26:$C$31,3,0),0) -> 0 | X12: =IFERROR(VLOOKUP(J12,$A$26:$C$31,3,0),0) -> 0 | Y12: =IFERROR(VLOOKUP(K12,$A$26:$C$31,3,0),0) -> 0 | Z12: =IFERROR(VLOOKUP(L12,$A$26:$C$31,3,0),0) -> 0 | AA12: =IFERROR(VLOOKUP(M12,$A$26:$C$31,3,0),0) -> 0 | AB12: =IFERROR(VLOOKUP(N12,$A$26:$C$31,3,0),0) -> 0 | AC12: =SUM(V12:AB12) -> 0
A13: 11 | O13: =COUNTIF(I13:N13,O$2) -> 0 | P13: =COUNTIF(I13:N13,P$2) -> 0 | Q13: =COUNTIF(I13:N13,Q$2) -> 0 | R13: =COUNTIF(I13:N13,R$2) -> 0 | S13: =COUNTIF(I13:O13,S$2) -> 0 | T13: =IF(COUNTBLANK(I13:N13)=6,0,IF(O13>0,$O$2,IF(P13>2,$O$2,IF(P13>0,$P$2,IF(Q13>2,$P$2,IF(Q13>0,$Q$2,IF(R13>2,$Q$2,IF(R13>0,$R$2,IF(S13>2,$R$2,$S$2))))))))) -> 0 | U13: =IFERROR(VLOOKUP(T13,$A$27:$B$31,2,0),0) -> 0 | V13: =IFERROR(VLOOKUP(H13,$A$26:$C$31,3,0),0) -> 0 | W13: =IFERROR(VLOOKUP(I13,$A$26:$C$31,3,0),0) -> 0 | X13: =IFERROR(VLOOKUP(J13,$A$26:$C$31,3,0),0) -> 0 | Y13: =IFERROR(VLOOKUP(K13,$A$26:$C$31,3,0),0) -> 0 | Z13: =IFERROR(VLOOKUP(L13,$A$26:$C$31,3,0),0) -> 0 | AA13: =IFERROR(VLOOKUP(M13,$A$26:$C$31,3,0),0) -> 0 | AB13: =IFERROR(VLOOKUP(N13,$A$26:$C$31,3,0),0) -> 0 | AC13: =SUM(V13:AB13) -> 0
A14: 12 | O14: =COUNTIF(I14:N14,O$2) -> 0 | P14: =COUNTIF(I14:N14,P$2) -> 0 | Q14: =COUNTIF(I14:N14,Q$2) -> 0 | R14: =COUNTIF(I14:N14,R$2) -> 0 | S14: =COUNTIF(I14:O14,S$2) -> 0 | T14: =IF(COUNTBLANK(I14:N14)=6,0,IF(O14>0,$O$2,IF(P14>2,$O$2,IF(P14>0,$P$2,IF(Q14>2,$P$2,IF(Q14>0,$Q$2,IF(R14>2,$Q$2,IF(R14>0,$R$2,IF(S14>2,$R$2,$S$2))))))))) -> 0 | U14: =IFERROR(VLOOKUP(T14,$A$27:$B$31,2,0),0) -> 0 | V14: =IFERROR(VLOOKUP(H14,$A$26:$C$31,3,0),0) -> 0 | W14: =IFERROR(VLOOKUP(I14,$A$26:$C$31,3,0),0) -> 0 | X14: =IFERROR(VLOOKUP(J14,$A$26:$C$31,3,0),0) -> 0 | Y14: =IFERROR(VLOOKUP(K14,$A$26:$C$31,3,0),0) -> 0 | Z14: =IFERROR(VLOOKUP(L14,$A$26:$C$31,3,0),0) -> 0 | AA14: =IFERROR(VLOOKUP(M14,$A$26:$C$31,3,0),0) -> 0 | AB14: =IFERROR(VLOOKUP(N14,$A$26:$C$31,3,0),0) -> 0 | AC14: =SUM(V14:AB14) -> 0
A15: 13 | O15: =COUNTIF(I15:N15,O$2) -> 0 | P15: =COUNTIF(I15:N15,P$2) -> 0 | Q15: =COUNTIF(I15:N15,Q$2) -> 0 | R15: =COUNTIF(I15:N15,R$2) -> 0 | S15: =COUNTIF(I15:O15,S$2) -> 0 | T15: =IF(COUNTBLANK(I15:N15)=6,0,IF(O15>0,$O$2,IF(P15>2,$O$2,IF(P15>0,$P$2,IF(Q15>2,$P$2,IF(Q15>0,$Q$2,IF(R15>2,$Q$2,IF(R15>0,$R$2,IF(S15>2,$R$2,$S$2))))))))) -> 0 | U15: =IFERROR(VLOOKUP(T15,$A$27:$B$31,2,0),0) -> 0 | V15: =IFERROR(VLOOKUP(H15,$A$26:$C$31,3,0),0) -> 0 | W15: =IFERROR(VLOOKUP(I15,$A$26:$C$31,3,0),0) -> 0 | X15: =IFERROR(VLOOKUP(J15,$A$26:$C$31,3,0),0) -> 0 | Y15: =IFERROR(VLOOKUP(K15,$A$26:$C$31,3,0),0) -> 0 | Z15: =IFERROR(VLOOKUP(L15,$A$26:$C$31,3,0),0) -> 0 | AA15: =IFERROR(VLOOKUP(M15,$A$26:$C$31,3,0),0) -> 0 | AB15: =IFERROR(VLOOKUP(N15,$A$26:$C$31,3,0),0) -> 0 | AC15: =SUM(V15:AB15) -> 0
A16: 14 | O16: =COUNTIF(I16:N16,O$2) -> 0 | P16: =COUNTIF(I16:N16,P$2) -> 0 | Q16: =COUNTIF(I16:N16,Q$2) -> 0 | R16: =COUNTIF(I16:N16,R$2) -> 0 | S16: =COUNTIF(I16:O16,S$2) -> 0 | T16: =IF(COUNTBLANK(I16:N16)=6,0,IF(O16>0,$O$2,IF(P16>2,$O$2,IF(P16>0,$P$2,IF(Q16>2,$P$2,IF(Q16>0,$Q$2,IF(R16>2,$Q$2,IF(R16>0,$R$2,IF(S16>2,$R$2,$S$2))))))))) -> 0 | U16: =IFERROR(VLOOKUP(T16,$A$27:$B$31,2,0),0) -> 0 | V16: =IFERROR(VLOOKUP(H16,$A$26:$C$31,3,0),0) -> 0 | W16: =IFERROR(VLOOKUP(I16,$A$26:$C$31,3,0),0) -> 0 | X16: =IFERROR(VLOOKUP(J16,$A$26:$C$31,3,0),0) -> 0 | Y16: =IFERROR(VLOOKUP(K16,$A$26:$C$31,3,0),0) -> 0 | Z16: =IFERROR(VLOOKUP(L16,$A$26:$C$31,3,0),0) -> 0 | AA16: =IFERROR(VLOOKUP(M16,$A$26:$C$31,3,0),0) -> 0 | AB16: =IFERROR(VLOOKUP(N16,$A$26:$C$31,3,0),0) -> 0 | AC16: =SUM(V16:AB16) -> 0
A17: 15 | O17: =COUNTIF(I17:N17,O$2) -> 0 | P17: =COUNTIF(I17:N17,P$2) -> 0 | Q17: =COUNTIF(I17:N17,Q$2) -> 0 | R17: =COUNTIF(I17:N17,R$2) -> 0 | S17: =COUNTIF(I17:O17,S$2) -> 0 | T17: =IF(COUNTBLANK(I17:N17)=6,0,IF(O17>0,$O$2,IF(P17>2,$O$2,IF(P17>0,$P$2,IF(Q17>2,$P$2,IF(Q17>0,$Q$2,IF(R17>2,$Q$2,IF(R17>0,$R$2,IF(S17>2,$R$2,$S$2))))))))) -> 0 | U17: =IFERROR(VLOOKUP(T17,$A$27:$B$31,2,0),0) -> 0 | V17: =IFERROR(VLOOKUP(H17,$A$26:$C$31,3,0),0) -> 0 | W17: =IFERROR(VLOOKUP(I17,$A$26:$C$31,3,0),0) -> 0 | X17: =IFERROR(VLOOKUP(J17,$A$26:$C$31,3,0),0) -> 0 | Y17: =IFERROR(VLOOKUP(K17,$A$26:$C$31,3,0),0) -> 0 | Z17: =IFERROR(VLOOKUP(L17,$A$26:$C$31,3,0),0) -> 0 | AA17: =IFERROR(VLOOKUP(M17,$A$26:$C$31,3,0),0) -> 0 | AB17: =IFERROR(VLOOKUP(N17,$A$26:$C$31,3,0),0) -> 0 | AC17: =SUM(V17:AB17) -> 0
A18: 16 | O18: =COUNTIF(I18:N18,O$2) -> 0 | P18: =COUNTIF(I18:N18,P$2) -> 0 | Q18: =COUNTIF(I18:N18,Q$2) -> 0 | R18: =COUNTIF(I18:N18,R$2) -> 0 | S18: =COUNTIF(I18:O18,S$2) -> 0 | T18: =IF(COUNTBLANK(I18:N18)=6,0,IF(O18>0,$O$2,IF(P18>2,$O$2,IF(P18>0,$P$2,IF(Q18>2,$P$2,IF(Q18>0,$Q$2,IF(R18>2,$Q$2,IF(R18>0,$R$2,IF(S18>2,$R$2,$S$2))))))))) -> 0 | U18: =IFERROR(VLOOKUP(T18,$A$27:$B$31,2,0),0) -> 0 | V18: =IFERROR(VLOOKUP(H18,$A$26:$C$31,3,0),0) -> 0 | W18: =IFERROR(VLOOKUP(I18,$A$26:$C$31,3,0),0) -> 0 | X18: =IFERROR(VLOOKUP(J18,$A$26:$C$31,3,0),0) -> 0 | Y18: =IFERROR(VLOOKUP(K18,$A$26:$C$31,3,0),0) -> 0 | Z18: =IFERROR(VLOOKUP(L18,$A$26:$C$31,3,0),0) -> 0 | AA18: =IFERROR(VLOOKUP(M18,$A$26:$C$31,3,0),0) -> 0 | AB18: =IFERROR(VLOOKUP(N18,$A$26:$C$31,3,0),0) -> 0 | AC18: =SUM(V18:AB18) -> 0
A19: 17 | O19: =COUNTIF(I19:N19,O$2) -> 0 | P19: =COUNTIF(I19:N19,P$2) -> 0 | Q19: =COUNTIF(I19:N19,Q$2) -> 0 | R19: =COUNTIF(I19:N19,R$2) -> 0 | S19: =COUNTIF(I19:O19,S$2) -> 0 | T19: =IF(COUNTBLANK(I19:N19)=6,0,IF(O19>0,$O$2,IF(P19>2,$O$2,IF(P19>0,$P$2,IF(Q19>2,$P$2,IF(Q19>0,$Q$2,IF(R19>2,$Q$2,IF(R19>0,$R$2,IF(S19>2,$R$2,$S$2))))))))) -> 0 | U19: =IFERROR(VLOOKUP(T19,$A$27:$B$31,2,0),0) -> 0 | V19: =IFERROR(VLOOKUP(H19,$A$26:$C$31,3,0),0) -> 0 | W19: =IFERROR(VLOOKUP(I19,$A$26:$C$31,3,0),0) -> 0 | X19: =IFERROR(VLOOKUP(J19,$A$26:$C$31,3,0),0) -> 0 | Y19: =IFERROR(VLOOKUP(K19,$A$26:$C$31,3,0),0) -> 0 | Z19: =IFERROR(VLOOKUP(L19,$A$26:$C$31,3,0),0) -> 0 | AA19: =IFERROR(VLOOKUP(M19,$A$26:$C$31,3,0),0) -> 0 | AB19: =IFERROR(VLOOKUP(N19,$A$26:$C$31,3,0),0) -> 0 | AC19: =SUM(V19:AB19) -> 0
A20: 18 | O20: =COUNTIF(I20:N20,O$2) -> 0 | P20: =COUNTIF(I20:N20,P$2) -> 0 | Q20: =COUNTIF(I20:N20,Q$2) -> 0 | R20: =COUNTIF(I20:N20,R$2) -> 0 | S20: =COUNTIF(I20:O20,S$2) -> 0 | T20: =IF(COUNTBLANK(I20:N20)=6,0,IF(O20>0,$O$2,IF(P20>2,$O$2,IF(P20>0,$P$2,IF(Q20>2,$P$2,IF(Q20>0,$Q$2,IF(R20>2,$Q$2,IF(R20>0,$R$2,IF(S20>2,$R$2,$S$2))))))))) -> 0 | U20: =IFERROR(VLOOKUP(T20,$A$27:$B$31,2,0),0) -> 0 | V20: =IFERROR(VLOOKUP(H20,$A$26:$C$31,3,0),0) -> 0 | W20: =IFERROR(VLOOKUP(I20,$A$26:$C$31,3,0),0) -> 0 | X20: =IFERROR(VLOOKUP(J20,$A$26:$C$31,3,0),0) -> 0 | Y20: =IFERROR(VLOOKUP(K20,$A$26:$C$31,3,0),0) -> 0 | Z20: =IFERROR(VLOOKUP(L20,$A$26:$C$31,3,0),0) -> 0 | AA20: =IFERROR(VLOOKUP(M20,$A$26:$C$31,3,0),0) -> 0 | AB20: =IFERROR(VLOOKUP(N20,$A$26:$C$31,3,0),0) -> 0 | AC20: =SUM(V20:AB20) -> 0
A21: 19 | O21: =COUNTIF(I21:N21,O$2) -> 0 | P21: =COUNTIF(I21:N21,P$2) -> 0 | Q21: =COUNTIF(I21:N21,Q$2) -> 0 | R21: =COUNTIF(I21:N21,R$2) -> 0 | S21: =COUNTIF(I21:O21,S$2) -> 0 | T21: =IF(COUNTBLANK(I21:N21)=6,0,IF(O21>0,$O$2,IF(P21>2,$O$2,IF(P21>0,$P$2,IF(Q21>2,$P$2,IF(Q21>0,$Q$2,IF(R21>2,$Q$2,IF(R21>0,$R$2,IF(S21>2,$R$2,$S$2))))))))) -> 0 | U21: =IFERROR(VLOOKUP(T21,$A$27:$B$31,2,0),0) -> 0 | V21: =IFERROR(VLOOKUP(H21,$A$26:$C$31,3,0),0) -> 0 | W21: =IFERROR(VLOOKUP(I21,$A$26:$C$31,3,0),0) -> 0 | X21: =IFERROR(VLOOKUP(J21,$A$26:$C$31,3,0),0) -> 0 | Y21: =IFERROR(VLOOKUP(K21,$A$26:$C$31,3,0),0) -> 0 | Z21: =IFERROR(VLOOKUP(L21,$A$26:$C$31,3,0),0) -> 0 | AA21: =IFERROR(VLOOKUP(M21,$A$26:$C$31,3,0),0) -> 0 | AB21: =IFERROR(VLOOKUP(N21,$A$26:$C$31,3,0),0) -> 0 | AC21: =SUM(V21:AB21) -> 0
A22: 20 | O22: =COUNTIF(I22:N22,O$2) -> 0 | P22: =COUNTIF(I22:N22,P$2) -> 0 | Q22: =COUNTIF(I22:N22,Q$2) -> 0 | R22: =COUNTIF(I22:N22,R$2) -> 0 | S22: =COUNTIF(I22:O22,S$2) -> 0 | T22: =IF(COUNTBLANK(I22:N22)=6,0,IF(O22>0,$O$2,IF(P22>2,$O$2,IF(P22>0,$P$2,IF(Q22>2,$P$2,IF(Q22>0,$Q$2,IF(R22>2,$Q$2,IF(R22>0,$R$2,IF(S22>2,$R$2,$S$2))))))))) -> 0 | U22: =IFERROR(VLOOKUP(T22,$A$27:$B$31,2,0),0) -> 0 | V22: =IFERROR(VLOOKUP(H22,$A$26:$C$31,3,0),0) -> 0 | W22: =IFERROR(VLOOKUP(I22,$A$26:$C$31,3,0),0) -> 0 | X22: =IFERROR(VLOOKUP(J22,$A$26:$C$31,3,0),0) -> 0 | Y22: =IFERROR(VLOOKUP(K22,$A$26:$C$31,3,0),0) -> 0 | Z22: =IFERROR(VLOOKUP(L22,$A$26:$C$31,3,0),0) -> 0 | AA22: =IFERROR(VLOOKUP(M22,$A$26:$C$31,3,0),0) -> 0 | AB22: =IFERROR(VLOOKUP(N22,$A$26:$C$31,3,0),0) -> 0 | AC22: =SUM(V22:AB22) -> 0
H23: =COUNTBLANK(H3:H22) -> 18 | I23: =COUNTBLANK(I3:I22) -> 20 | J23: =COUNTBLANK(J3:J22) -> 20 | K23: =COUNTBLANK(K3:K22) -> 20 | L23: =COUNTBLANK(L3:L22) -> 20 | M23: =COUNTBLANK(M3:M22) -> 20 | N23: =COUNTBLANK(N3:N22) -> 20
O24: =SUM(O3:O22) -> 0 | P24: =SUM(P3:P22) -> 0 | Q24: =SUM(Q3:Q22) -> 0 | R24: =SUM(R3:R22) -> 0 | S24: =SUM(S3:S22) -> 0 | U24: =SUM(U3:U22) -> 0
B25: Costo Fabrica Desarrollo | M25: Resultado | T25: =IF(O24>0,$O$2,IF(P24>2,$O$2,IF(P24>0,$P$2,IF(Q24>2,$P$2,IF(Q24>0,$Q$2,IF(R24>2,$Q$2,IF(R24>0,$R$2,IF(S24>2,$R$2,$S$2)))))))) -> XS | U25: =CONCATENATE(U24," semanas") -> 0 semanas | AC25: =SUM(AC3:AC22) -> 0
B26: Semanas | C26: Costo | D26: Descipción | F26: Fabrica
A27: XS | B27: 1 | C27: 165000 | D27: Costo de Fabrica por 1 semana | F27: 2 DEV
A28: S | B28: 2 | C28: =C27*2 -> 330000 | D28: Costo de Fabrica por 2 semana | F28: 2 DEV, 2 GES, 1 ARQ y 1 LT
A29: M | B29: 4 | C29: =C28*2 -> 660000 | D29: Costo de Fabrica por 4 semanas | F29: 2 DEV, 2 GES, 1 ARQ y 1 LT
A30: L | B30: 6 | C30: 990000 | D30: Costo de Fabrica por 6 semanas | F30: 2 DEV, 2 GES, 1 ARQ y 1 LT
A31: XL | B31: 8 | C31: 1320000 | D31: Costo de Fabrica por 8 semanas | F31: 2 DEV, 2 GES, 1 ARQ y 1 LT

Sheet Arquitectura
K1: Arquitectura To be Contextual
B2: El TPO con apoyo de su proveedor del servicio deberá colocar la arquitectura to be contextual

Sheet Roles
B2: Roles sin Costo
B4: Roles sin Costo | E4: Num colaboradores | F4: Semanas | H4: Semanas Adicionales
B5: Coordinador de Portafolio de Proyectos | C5: OPTI | D5: SI | E5: 1 | F5: ='Epic Backlog'!$U$24+H5 -> 0 | H5: 0
B6: Product Owner | C6: OP | D6: SI | E6: 1 | F6: ='Epic Backlog'!$U$24+H5 -> 0
B7: Arquitecto de Soluciones | C7: NS | D7: SI | E7: 1 | F7: ='Epic Backlog'!$U$24+$H$5 -> 0
C9: Num colaboradores | D9: Semanas
B10: TPO | C10: =IF('Epic Backlog'!H23<20,2,1) -> 2 | D10: ='Epic Backlog'!$U$24+$H$5 -> 0
B11: Coordinador de Soluciones | C11: =IF('Epic Backlog'!H23<20,2,1) -> 2 | D11: ='Epic Backlog'!$U$24+$H$5 -> 0
B12: Líder Técnico | C12: =SUM(F12:K12) -> 1 | D12: ='Epic Backlog'!$U$24+$H$5 -> 0 | F12: =IF('Epic Backlog'!H23<20,1,0) -> 1 | G12: =IF('Epic Backlog'!I23<20,1,0) -> 0 | H12: =IF('Epic Backlog'!J23<20,1,0) -> 0 | I12: =IF('Epic Backlog'!K23<20,1,0) -> 0 | J12: =IF('Epic Backlog'!L23<20,1,0) -> 0 | K12: =IF('Epic Backlog'!M23<20,1,0) -> 0 | L12: =IF('Epic Backlog'!N23<20,1,0) -> 0
B15: Roles con Costo
B17: Rol | D17: Requerido | E17: Num colaboradores | F17: Costo Unitario | G17: Semanas | H17: Costo
B18: Scrum Master / PM | C18: OPTI | D18: SI | E18: =IF(D18="SI",1,0) -> 1 | F18: =IF(D18="NO", 0,28000) -> 28000 | G18: ='Epic Backlog'!$U$24+$H$5 -> 0 | H18: =(F18*G18)*E18 -> 0
B19: Líder Infraestructura + SRE (sin observabilidad) | C19: DOTI | D19: NO | E19: =IF(D19="SI",1,0) -> 0 | F19: 44245 | G19: ='Epic Backlog'!$U$24+$H$5 -> 0 | H19: =((IF(J19=0,INT(I19),INT(I19)+1))*F19)*E19 -> 0 | I19: =G19/4 -> 0 | J19: =ROUND((I19 - INT(I19)) * 10^LEN(FIXED(I19)), 0) -> 0
B20: Líder Infraestructura + SRE (con observabilidad) | C20: DOTI | D20: SI | E20: =IF(D20="SI",1,0) -> 1 | F20: 57245 | G20: ='Epic Backlog'!$U$24+$H$5 -> 0 | H20: =((IF(J20=0,INT(I20),INT(I20)+1))*F20)*E20 -> 0 | I20: =G20/4 -> 0 | J20: =ROUND((I20 - INT(I20)) * 10^LEN(FIXED(I20)), 0) -> 0
B21: Líder Técnico de Seguridad | C21: SEG | D21: SI | E21: =IF(D21="SI",1,0) -> 1 | F21: =IF('Epic Backlog'!T25="L",22500,IF('Epic Backlog'!T25="XL",22500,0)) -> 0 | G21: ='Epic Backlog'!$U$24+$H$5 -> 0 | H21: =(F21*G21)*E21 -> 0
B24: FABRICA DE PRUEBAS (QA)
B25: Rol | D25: Requerido | E25: Num colaboradores | F25: Costo Unitario | G25: Semanas | H25: Costo
B26: Líder de Pruebas | C26: FS | D26: SI | E26: =IF(D26="SI",1,0) -> 1 | F26: =(650*40) -> 26000 | G26: ='Epic Backlog'!$U$24+$H$5 -> 0 | H26: =(F26*G26)*E26 -> 0
B27: Tester | C27: FS | D27: SI | E27: =IF(D27="SI",1,0) -> 1 | F27: =(900*40) -> 36000 | G27: ='Epic Backlog'!$U$24+$H$5 -> 0 | H27: =(F27*G27)*E27 -> 0
F29: Resultado | H29: =H27+H26+H21+H19+H18+H20 -> 0

Sheet Cuestionario
B2: # | C2: Tema | D2: Pregunta | E2: Respuestas | F2: Talla | G2: Costo Anual | H2: Respuesta | I2: Monto
B3: 1 | C3: Infraestructura | D3: Define el tipo de Infraestructura y su alcance * Si se requiere Alta Disponibilidad (Redundancia) contactar a Operaciones | E3: Solución critica/Core de Negocio Cloud Tipos de componentes Servidor, BD, contenedores, microservicios. Más de 10 componentes. Conectividad de plataformas >3 On Premise 4 servidores virtuales, 2 servidores físicos y 3 bases de datos. Redes Conectividad hacia la red (+ enlace wan, incluye un switch y la configuración) | F3: XL | G3: 2415656.7 | I3: =IFERROR(VLOOKUP(H3,F3:G8,2,0),0) -> 0
E4: Producto con integración con más de 3 aplicaciones actuales Cloud Tipos de componentes Servidor, BD, de 7 a 9 componentes, Conectividad de plataformas >3 On Premise 5 servidores virtuales, 1 base de datos Redes Esta talla incluye la conectividad de red (configuración, al ser servidores virtuales no requiere switch) | F4: L | G4: 1215656.7
E5: Producto desarrollado por proveedor para un área de negocio especifica Cloud Tipos de componentes Servidores, BD´s. De 5 a 7 componentes. Conectividad de plataformas = 3 On Premise 3 servidores virtuales, 1 base de datos Redes Esta talla incluye la conectividad de red (configuración, al ser servidores virtuales no requiere switch) | F5: M | G5: 615656.72
E6: Producto con integración a 1-2 satélites Cloud Tipos de componentes Servidor. De 4 a 5 componentes. Conectividad de plataformas 1 a 2. On Premise 2 servidores virtuales. 1 base de datos Redes Esta talla incluye la conectividad de red (configuración, al ser servidores virtuales no requiere switch) | F6: S | G6: 375656.72
E7: Producto sin integración a satélites Cloud Tipos de componentes Servidor. De 1 a 3 componentes. Conectividad plataformas: Independiente. Incremento de capacidad en componente existente On Premise 1 servidor virtual Redes Esta talla incluye la conectividad de red (configuración, al ser servidor virtual no requiere switch) | F7: XS | G7: 255656.72
E8: NA | F8: NA | G8: NA
B9: 2 | C9: Licencias de Monitoreo (On Premise AppDynamics o Cloud Data Dog) + SNow componente | D9: ¿Se requiere monitoreo de aplicaciones? | E9: Monitoreo On Premise o Nube: Producto con conectividad con mas de 3 plataformas y mas de 10 componentes (contenedores, DBs, Servidores, etc) | F9: XL | G9: 496934.04 | I9: =IFERROR(VLOOKUP(H9,F9:G14,2,0),0) -> 0
E10: Monitoreo On Premise o Nube: Producto con conectividad a mas de 3 plataformas, 7 a 9 componentes. | F10: L | G10: 309718.56
E11: Monitoreo On Premise o Nube: Producto con conectividad con 3 plataformas, 5 a 7 componentes. | F11: M | G11: 201679.08
E12: Monitoreo On Premise o Nube: Producto desarrollado por un proveedor con un integración de 1 o 2 plataformas, 4 a 5 componentes | F12: S | G12: 108039.6
E13: Monitoreo On Premise o Nube: Sin integración a plataformas, de 1 a 3 componentes, conectividad independiente. | F13: XS | G13: 52428.84
E14: NA | F14: NA | G14: NA
B15: 3 | C15: Licencias de bases de datos OnPremise (SO, BD y Entorno Digital) | D15: ¿Se requieren BD nuevas para su solución, ya sea Oracle o SQL? (Se consideran las licencias de SO, BD y Entorno Digital) | E15: Producto en Oracle con integración con 6 o más plataformas (Para XL, servidores físicos, no se recomienda SQL). | F15: XL | G15: 348726.8 | I15: =IFERROR(VLOOKUP(H15,F15:G20,2,0),0) -> 0
E16: Producto (BD Oracle o SQL) con intrgración a 4 a 5 plataformas | F16: L | G16: 225752.67
E17: Producto (BD Oracle o SQL) con integración con 3 plataformas. | F17: M | G17: 158726.4
E18: Producto (BD Oracle o SQL) con un integración con 2 componentes | F18: S | G18: 131453.27
E19: Producto (BD Oracle o SQL) con integración a 1 plataforma. | F19: XS | G19: 27273.13
E20: NA | F20: NA | G20: NA
B21: 4 | C21: Especialistas dedicados para instalación de ambientes y PFTs, (2 meses) Opcional | D21: ¿Se requieren especialistas dedicados para instalar ambientes? Y para pruebas funcionales? Se sugiere estimar al menos 2 meses | E21: Especialistas 100 hrs x mes (Bolsa de horas L3, L2, DBA) | F21: XL | G21: 150000 | I21: =IFERROR(VLOOKUP(H21,F21:G26,2,0),0) -> 0
E22: Especialistas 80 hrs x mes (Bolsa de horas L3, L2, DBA) | F22: L | G22: 120000
E23: Especialistas 60 hrs x mes (Bolsa de horas L3, L2, DBA) | F23: M | G23: 90000
E24: Especialistas 40 hrs x mes (Bolsa de horas L3, L2, DBA) | F24: S | G24: 60000
E25: NA | F25: XS | G25: NA
E26: NA | F26: NA | G26: NA
B27: 5 | C27: Pruebas de Seguridad | D27: Con base en la complejidad del proyecto se requieren pruebas de seguridad | E27: Elegir de acuerdo al tamaño de la iniciativa | F27: XL | G27: 400000 | I27: =IFERROR(VLOOKUP(H27,F27:G31,2,0),0) -> 0
E28: Elegir de acuerdo al tamaño de la iniciativa | F28: L | G28: 300000
E29: Elegir de acuerdo al tamaño de la iniciativa | F29: M | G29: 200000
E30: Elegir de acuerdo al tamaño de la iniciativa | F30: S | G30: 100000
E31: NA | F31: XS | G31: 50000
G33: Resultado | I33: =SUM(I2:I31) -> 0

Sheet Resultado
A1: Calculadora T-SHIRT 1.3 PAM
A6: Tiempo E2E Aprox | B6: =CONCATENATE('Epic Backlog'!U24+Roles!H5," Semanas") -> 0 Semanas | E6: =IF(F6=G6,1,0) -> #N/A | F6: MVP3 | G6: =VLOOKUP(F6,'Epic Backlog'!E1:E22,1,0) -> #N/A | H6: Fecha de elaboración | J6: {='Proc de Neg (To-Be)'!E5:K5} -> 45891 | K6: 0 | L6: 0 | M6: 0 | N6: 0 | O6: 0 | P6: 0
A7: Costo Promedio | B7: ='Epic Backlog'!AC25+Cuestionario!I33+Roles!H29 -> 0 | E7: =IF(F7=G7,1,0) -> #N/A | F7: MVP2 | G7: =VLOOKUP(F7,'Epic Backlog'!E1:E22,1,0) -> #N/A | H7: Nombre de iniciativa | J7: {='Proc de Neg (To-Be)'!E3:K3} -> Recaudo de Servicios con BBVA | K7: 0 | L7: 0 | M7: 0 | N7: 0 | O7: 0 | P7: 0
A8: Complejidad | B8: ='Epic Backlog'!T25 -> XS | E8: =IF(F8=G8,1,0) -> 1 | F8: MVP1 | G8: =VLOOKUP(F8,'Epic Backlog'!E1:E22,1,0) -> MVP1
A9: Cantidad de MVP´s | B9: =IFERROR(VLOOKUP(1,E6:G8,3,0),0) -> MVP1 | H9: Notas
E10: Tipo de Cambio | F10: 20
A11: Costos Adicionales
A13: Concepto | C13: Monto MXN | D13: Monto USD | E13: Descripción
A14: Infraestructura
A15: Servicios con Terceos
A16: Licenciamiento
A17: Soporte
A18: Costo A
A19: Costo B
C20: =SUM(C14:C19) -> 0 | D20: =SUM(D14:D19) -> 0
E22: Monto MXN | G22: Monto USD
C23: Costo Total | E23: =B7+C20+(D20*F10) -> 0 | G23: =E23/F10 -> 0
A24: SI INICIAL | E24: =E23*0.3 -> 0 | G24: =E24/F10 -> 0

Sheet Hoja1
A1: Nombre Epica | B1: Descripción | C1: Criterios de Aceptación | D1: MVP en el que se estima se desarrolle | E1: Historas de Usuario | F1: Descripción | G1: Criterios de aceptación | H1: Supuesto | I1: Reglas de negocio | J1: Riesgo
G2: Criterios de aceptación | H2: Supuestos | I2: Reglas de Negocio | J2: Riesgo
A3: Geo- Habilitación de la autopista de servicios | B3: Como negocio, quiero contar con una carretera que integre la recaudación de los servicios desde el punto de venta hasta el EBS. | C3: Debe soportar comisiones fijas, variales, porcentuales, etc que el partner nos indique y debe ser configurables. Contar con la configuración de servicios en la caja de servicios propia de Geo. Replicar la configuración del servicio de manera automática en una tabla customizada que estará alojada en EBS. Debe enviar la información para la contabilización. Debe enviar información de manera diaria a Reportería BI (ODS) Debe generar el archivo de cierre de día. Debe generar el resumen operativo. Registro en la tabla GL_Interface de EBS (Conciliaciones administrativas). | D3: MVP1 | E3: HU1– Configuración de servicios - configuracion de datos basicos | F3: Como negocio quiero contar con una consola o portal donde se puedan realizar las configuraciones y mantenimientos de los datos basicos de los servicios, ya sea de forma individual o por carga masiva. | G3: El portal debe permitir crear, editar y eliminar datos básicos de los servicios. Debe permitir carga individual y carga masiva. Cada servicio debe tener un identificador único. Los campos para la configuración se encuentran el la hoja 2 | H3: Los usuarios tienen perfiles con permisos para configurar. Los catálogos maestros (moneda, tipo de servicio, etc.) están disponibles. | I3: Todos los servicios deben ser identificados con un código único Solo los usuarios con rol administrador pueden realizar configuraciones y mantenimientos. | J3: Datos inconsistentes si se cargan servicios duplicados. Registro o carga sin validación previs.
E4: HU2 – Configuración de servicios - configuracion de reglas de visualizacion en el front | F4: Como negocio quiero contar con una consola o portal donde se puedan realizar las configuraciones de las reglas de visualizacion para el front para que el cajero pueda seleccionar las opciones para el pago de los servicios. | G4: Debe existir un portal para definir las reglas de visualización en el front. El cajero debe ver únicamente los servicios activos y habilitados. | H4: GeoPOS soporta el consumo de las reglas de visualización. | I4: Solo los servicios con estado “activo” deben mostrarse en el front. La jerarquía de visualización debe ser configurable. | J4: Posible error en la visualización si la regla no está bien configurada. Confusión del cajero si aparecen servicios inactivos.
E5: HU3 – Configuración de servicios - configuracion de reglas de negocio para la exportacion a GL Interface | F5: Como negocio quiero contar con una consola o portal donde se puedan realizar las configuraciones de las reglas de negocio para que se exporten los datos de acuerdo a las condiciones comerciales. | G5: Debe poder configurarse la regla contable del servicio. La exportación debe respetar la regla definida. | H5: Las cuentas contables están disponibles y actualizadas. | I5: Cada servicio debe tener asignada una regla de exportación antes de activarse. | J5: No exportar datos a GL si la regla está incompleta. Errores en conciliación si las reglas no coinciden con lo solicitado por el negocio.
E6: HU4 – Configuración de servicios - configuracion para la exportacion de las cuentas contables | F6: Como negocio quiero contar con una consola o portal donde se pueda realizar la configuracion de las cuentas contables para una conciliacion correcta. | G6: El portal debe permitir asignar cuentas contables de los servicio. Validar que las cuentas ingresadas existan en el módulo contable de EBS. | H6: El cmódulo contable de EBS está sincronizado con el portal. | I6: Ningún servicio puede estar activo sin cuenta contable asociada. | J6: Error en conciliación administrativa por cuentas mal configuradas.
E7: HU5 - Replica de alta de servicio en tabla Custom de EBS | F7: Como negocio requiero poder tener en EBS una tabla custom de la configuración de los Servicios la cuál debe actualizarse de manera automática cada que haya una actualización o un registro nuevo desde GEO, los campos a considerar son: (poner todos los campos que dijimos viajan a EBS) | G7: Los servicios creados en el portal deben replicarse automáticamente en la tabla custom de EBS. Confirmación de réplica exitosa debe registrarse. | H7: Existe conectividad estable entre el portal y EBS. | I7: La réplica debe realizarse en tiempo real | J7: Pérdida de sincronización si falla la réplica. Inconsistencias entre portal y EBS.
E8: HU6- Envío de servicios a tiendas (GeoPOS) | F8: Como negocio quiero que se muestre en Geopos el menú de servicios para que los cajeros puedan realizar el proceso de pagos de los servicios disponibles. | G8: Los servicios configurados con estado activo deben mostrarse en GeoPOS. El cajero podrá visualizar y cobrar únicamente los servicios activos y con reglas configuradas. GeoPOS debe mantener conectividad constante con el servidor de configuración para obtener la lista de servicios actualizada. Si GeoPOS no recibe la información del servicio, el cajero no podrá procesar el cobro. | H8: Existe un endpoint de configuración (API) disponible 24/7 que retorna la lista de servicios y reglas. Se mantiene el catálogo de servicios actualizado. | I8: Solo servicios Activos y con reglas de cobro vigentes se muestran. La Sincronización automática debe ser programada. | J8: EConfiguración errónea puede crear cobros incorrectos. Falta de registro dificulta poder rastrear errores.
E9: HU7- Integración de datos hacia GL (EBS) | F9: Como negocio quiero que en la ejecución del fin día de la tienda, se realice la exportación de la información de servicios para la integración a GL, en base a la configuración del alta de los servicios y se asocien a las cuentas contables correspondientes. | G9: Se exporta la información contable del día en formato válido GL_Interface. No se exporta ninguna transacción sin cuenta contable válida. Proceso automático al cierre de día; transacciones rechazadas debe quedae en log o evidencia. | H9: Existe la especificación actualizada de GL_Interface (EBS) y acceso para ingestión de archivos. El cierre de día de la tienda se ejecuta después del proceso de todas las transacciones del día. | I9: Cada servicio debe tener cuenta contable configurada antes de integrarse. Validación de existencia de cuentas contables activas antes del envío. Solo transacciones confirmadas, activas y conciliadas se exportan. | J9: Información incompleta que impida contabilización en EBS. Fallo de transferencia puede no generar la contabilidad. Cambio de esquema en EBS puede generar rechazo de archivos.
E10: HU8- Exportación de información a reportería (ODS/BI) | F10: Como negocio quiero recibir la información de los servicios recibidos en tienda como insumo para la reportería BI para el análisis y conciliaciones. | G10: Envío diario de datos a ODS/BI con el formato requerido. La reportería incluye toda la información de los servicios cobrados durante el día. Errores de transmisión o registros incompletos deben quedar documentados. Debe permitir exponer el detalle de la comisión. | H10: BI está habilitado para recibir datos en el formato requerido. | I10: La reportería debe incluir todos los servicios cobrados durante el día. Solo se enviarán transacciones con estado finalizado. Validación de integridad y consistencia antes del envío. ODS/BI debe estar habilitado para recibir el esquema requerido. | J10: Información incompleta en BI afecta conciliaciones y reportes. Exposición de datos sensibles daria un incumplimiento de privacidad
E11: HU9-Almacenamiento de las negociaciones y contratos comerciales | F11: Como negocio quiero contar con una base de datos de las negociaciones y contratos comerciales a la configuracion de cada servicio. | G11: Registrar, consultar y actualizar negociaciones y contratos por servicio. Cada contrato indica vigencia, proveedor y condiciones comerciales. Solo contratos vigentes pueden asociarse a servicios activos. Control de versiones/histórico de cambios por contrato. | H11: Se cargarán contratos en la plataforma. Existe un identificador único para contratos y para servicios. Los accesos y permisos para ver/editar contratos deben estar definidos. | I11: Toda configuración de servicio debe estar vinculada a una negociación o contrato activo. Los contratos debe tener estado activo y desactivado Validar de fecha de ingreso del contrato y finalización Controlar las versiones de cambio. Se debe generar una alerta cuando este proximo a vencer el contrato. Se define los perfiles de acceso para la verificación y edición del contrato. | J11: Contratos no vinculados o mal vinculados puede generar operaciones incorrectas. Contratos vencidos activos puede generar condiciones obsoletas.
A12: Geo-Recaudo de servicios | B12: Como cajero quiero poder consultar, validar y ejecutar el pago de los servicios relizados por el cliente. | C12: Conectarse con el operador del servicio (BBVA). Habilitar los servicios para el cobro mediante los medios de pago respectivo. Cuando ocurra un error de conectividad, debe mostrarse alerta/mensaje al cajero en el POS. Tener la opción de invocar el nombre del servicio que desea pagar (buscador). Contar con un listado de las opciones de los servicios invocados para el servicio a pagar. Seleccionar el servicio que el cliente desea pagar. Permitir ingresar datos asociados al servicio (item del convenio/Recaudo). Mostrar el detalle del servicio a pagar. Permitir generar la simulación de pago para la validación del cliente. Ejecutar de un pago a más de acuerdo a las especificaciones del servicio. No se permite anulaciones después del pago del servicio. | D12: MVP1 | E12: H10 - Geo-Cierre de turno y Cierre de día | F12: Como cajero, quiero que se visualice en el cierre de turno y de día en el POS, para consolidar las operaciones registradas. | G12: Debe generarse reporte de cierre de turno y cierre de día. Los servicios cobrados deben estar acorde al cuadre de caja. El cajero debe poder ejecutar el proceso de cierre correctamente. | H12: El cajero ejecuta el proceso de cierre correctamente. | I12: No se puede abrir un nuevo turno sin realizar el cierre del anterior. El cierre de turno se realiza solo si se hace un cambio de turno. El cierre de día se realiza según regla de negocio actual. | J12: Descuadre contable si el cierre no se genera correctamente.
E13: H11 - Geo-Resumen Operativo | F13: Como negocio, quiero generar un resumen operativo en el POS, para tener visibilidad de todas las transacciones realizadas. | G13: Los datos de cierre de día deben estar correctamente consolidados. El resumen debe incluir todas las transacciones del día. Toda la información transaccional debe ser registrada en el POS. | H13: Los datos de cierre de día están correctamente consolidados. | I13: El resumen operativo debe incluir los filtros según requerimiento de oxxo. | J13: Posible inconsistencia entre el resumen y los reportes de cierre si no se validan los datos.
E14: HU12- Llamado a la opción de Recaudos de Servicios (F5) | F14: Como cajero, quiero acceder al módulo de recaudos desde el POS, para iniciar el proceso de cobro de servicios. | G14: La tecla F5 debe estar habilitado para mostrar la lista de tipo de servicios en el front POS. El sistema debe mostrar en pantalla luego del llamado F5 los tipos de servicio. Debe estar dentro de la lista de los tipo de servicio la opción Recaudo de servicio BBVA. Al seleccionar la opción de Recaudo de servicio BBVA debe enviar a la pantalla para la Busqueda del servicio que se desea pagar. | H14: El POS cuenta con la funcionalidad habilitada. El POS tiene habilitado la opción al llamado f5 | I14: Solo usuarios autenticados pueden acceder al módulo. El llamado al tipo de servicio, opción Recaudo de servicio debe ser por el f5. Todos los servicios de recaudos BBVA deben estar integrados en el llamado f5 | J14: Error de mapeo de teclas en el POS.
E15: HU13- Búsqueda de servicio a pagar | F15: Como cajero, quiero que al ingresar un criterio de busqueda me liste los servicios que coincidan para poder seleccionar el servicio a pagar. | G15: El sistema debe permitir ingresar los caracteres para la búsqueda. El sistema debe permitir ingresar nombre parcial o completo del servicio. El sistema debe invocar la API de BBVA y devolver listado de servicios coincidentes. Para obtener el resultado de los servicios el sistema debe tener conexión con el proveedor de servicios. Si la conexión falla, debe mostrar mensaje de error . La conexión debe darse para llamar a los servicios que estan dados de alta para el pago correspondiente. | H15: El catálogo de servicios está sincronizado con BBVA. El recaudador tiene disponibilidad 24/7. | I15: Solo se pueden mostrar los servicios habilitados en BBVA. Solo se pueden pagar los servicios habilitados en BBVA. No se permite iniciar pago si no hay conexión con el recaudador. Se requeire la conexión con el recaudador y el servicio. | J15: Lista incompleta o desactualizada. El servicio no este activo Caída del servicio externo impide iniciar el proceso.
E16: HU14- Control multiple de opciones de busqueda del servicio a pagar | F16: Como cajero, quiero que me liste todos los servicios asociados a la búsqueda para localizar el servicio más rápidamente. | G16: El sistema debe mostrar la lista de los servicios asociados a la búsqueda. Se debe mostrar el listado de los servicios que se encuentran dados de alta. El listado debe permitir seleccionar solo una opción. | H16: Los servicios se podrán buscar por palabra completa o parcial | I16: No debe mostrar duplicidad de servicios Se muestra la lista de los servicios asociados a la búsqueda Debe mostrar solo los servicios dados de alto asociados a la búsqueda. Al seleccionar el servicio a pagar debe derivar al módulo para ingresar el dato identificador para el llamado del servicio. | J16: Duplicidad de resultados que confunda al cajero.
E17: HU15- Permite ingresar el identificador del servicio (alfanumérico) por tipo de convenio | F17: Como cajero, quiero ingresar el identificador alfanumérico del cliente , o los datos que se requiera de acuerdo al tipo de convenio para validar y consultar los recibos pendientes que expone el servicio. | G17: El campo debe aceptar letras y números según tipo de convenio o lo que solicite el recaudo en la API. Si el identificador es inválido, mostrar mensaje de error. Los datos de identificación para el llamado a consultar el recibo del servicio debe ser ingresado en los campos según convenio (Base de datos, Interconectado, Data Entry, Tasas fijas). El sistema debe permitir solicitar el código identificador del cliente, en caso no coincida enviar un mensaje de alerta por el error en el código de identificación. | H17: Cada servicio define su tipo de identificador. | I17: Cada servicio tiene asociado su tipo de convenio. Cada servicio está asociado a un tipo de convenio para que valide el identificador. El sistema no debe permitir continuar con identificador inválido El identificador debe estar asociado al servicio. Solo permite consultar el recibo si el servicio esta dado de alta. Los campos que se muestra para consultar el recibo debe estar asociado al tipo de convenio (Los tipos de convenio son: Base de datos, Interconectado, Data Entry, Tasas fijas.) Para el caso de Data Entry debe solicitar los campos identificador (alfanumérico) e importe para completar el pago del servicio. No muestra los pagos pendientes para el caso de Data Entry . | J17: Error humano al digitar identificadores.
E18: HU16- Mostrar información del servicio a cobrar | F18: Como cajero, quiero visualizar los datos del servicio y cliente, para confirmar que corresponde al recibo correcto. | G18: Debe mostrarse los datos del servicio, datos del cliente y montos a pagar, fecha de acuerdo al tipo de convenio (Base de datos, Interconectado, Data Entry, Tasas fijas). Mostrar la información expuesta por la APi para el pago de servicio. Para el caso de servicios con tipo de convenio Base de datos e Interconectados la APi puede exponer pagos unicos, pagos múltiples o realizar pagos parciales. Para el caso de servicios con tipo de convenio Data entry al ser un ingreso manual de datos, no expone pagos pendientes. Para el caso de servicios con tipo de convenio Tasas fijas debe exponer el importe fijo o permitir un importe flexible | H18: BBVA envía la información actualizada. | I18: La transacción se puede mostrar para realizar los pagos de acuerdos a lo que expone el api de servicios : un solo pago, pago múltiple, pagos parciales y editar monto. Debe permitir seleccionar los montos que se desea pagar en caso de pago múltiple. La selección de los pago debe darse de los mas antiguo a lo actual o dependiendo lo que exponga la API. | J18: Inconsistencia entre datos del proveedor y BBVA.
E19: HU17- Permite realizar y mostrar una simulación de pago | F19: Como cajero, quiero ejecutar una simulación de pago antes de cobrar, para confirmar con el cliente el monto total de la transacción. | G19: El sistema debe invocar el API de simulación y devolver el resultado. Debe mostrarse desglose: servicio, recibo, monto y comisión (si aplica) y los demas datos que expone la API. Para los casos de Data Entry la simulación es en baso a los datos ingresados de acuerdo a lo que solicita la API. El cajero debe tener la alternativa de aceptar o rechazar la simulación. En caso que el cajero indique ESC la simulación debe mostrar la pantalla anterior a la simulación. Cuando se acepte debe mostrar la pantalla de ingreso de artículos con el item ingresado. | H19: El API responde en tiempo razonable. El API envía la información correcta | I19: Ningún pago real se ejecuta sin simulación previa. | J19: Aprobación errónea si la simulación no se valida.
E20: HU18- Ejecución del pago en efectivo | F20: Como cajero, quiero registrar el pago en efectivo tras la conformidad del cliente, para completar la transacción. | G20: Ante timeout o error 500, el sistema debe mostrar mensaje: “Error de conexión, intente nuevamente.” El botón de reintento debe estar disponible en la pantalla principal sin reiniciar todo el flujo. El sistema debe perimitir 5 reintentos antes de reiniciar el proceso. Los reintentos deben registrarse en logs. | H20: El cajero puede realizar la transacción en efectivo | I20: Solo se permiten pagos en efectivo. Los pagos en efectivo se realizan de acuerdo al limite del monto estimado por OXXO. Los límites de monto deben ser configurables. | J20: Se realiace un pago con monto erroneo
E21: HU19 – Impresión del comprobante | F21: Como cajero, quiero imprimir un comprobante del pago, para entregarlo al cliente como constancia. | G21: El comprobante debe incluir los datos del servicio, de OXXO, cajero y medio de pago.( Ver Hoja2 para el comprobante) Debe imprimirse automáticamente tras confirmación. Debe imprimirse luego de la validación con el cliente. | H21: La impresora del POS está operativa. | I21: El comprobante es obligatorio en cada transacción. la estructura de comprobante se define por cada tipo de convenio | J21: Fallo de impresora Fallo en la comunicación de los datos del comprobante
E22: HU20-Reflejo de pago en BBVA y proveedor tercero | F22: Como negocio, quiero que el sistema envíe la confirmación de pago a BBVA y al proveedor, para reflejar la operación en ambas partes de acuerdo al tipo de convenio del recaudo. | G22: El sistema debe enviar confirmación de pago exitosa a BBVA. El sistema debe enviar confirmación de pago exitosa al proveedor tercero de acuerdo al tipo de convenio. Si alguna confirmación falla, debe quedar registrado. | H22: BBVA cuenta con servicios disponibles lo cual los expone mediante las APIs . La conexión de red con el recaudo es estable. | I22: El pago se considera exitoso solo si BBVA confirma la transacción. En caso de error, el sistema debe priorizar la conciliación posterior. | J22: Fallo en comunicación con BBVA
E23: HU21- Control de límite del monto a pagar | F23: Como cajero quiero que el sistema valide un límite máximo de monto permitido para pagos en efectivo en caja , para garantizar la seguridad operativa, cumplir con las políticas internas y minimizar el riesgo de exposición a robos o fraudes. | G23: El sistema debe validar que ningún pago en efectivo supere el monto máximo definido. Si un cliente intenta pagar un monto superior, el sistema debe mostrar un mensaje de alerta indicando que se excede el límite. El sistema debe permitir configurar el monto máximo de pago de forma parametrizable | H23: Inicialmente los pagos serán solo en efectivo GEO generará las alertas de control de límite y resguardo de montos | I23: Ningún pago podrá exceder el monto máximo configurado por transacción El monto límite debe ser configurable Los pagos que superen el límite deben ser rechazados automáticamente con mensaje al cajero. Debe mostrar un mensaje por exceso de limite en caja y gaveta. Debe mostrar un mensaje por exceso de limite de pago en soles. | J23: Configuración incorrecta de los límites
E24: HU22- Opción de reintento de pago por time out - error 500 (fila 211) ( que vuelva a la pantalla principal) | F24: Como cajero, quiero recibir una alerta clara si ocurre un error de conectividad y poder reintentar el pago cuando ocurra un timeout o error 500, antes de reiniciar el proceso | G24: Ante timeout o error 500, el sistema debe mostrar mensaje: “Error de conexión, intente nuevamente.” El botón de reintento debe estar disponible en la pantalla principal sin reiniciar todo el flujo. El sistema debe perimitir 5 reintentos antes de reiniciar el proceso. Los reintentos deben registrarse en logs. | H24: Los errores 500 provienen de fallas en la integración o comunicación externa. | I24: El reintento solo es válido si la transacción previa no fue confirmada por el Recaudador/proveedor. El reintento debe permitirse realizar 5 veces antes de volver a iniciar el proceso. No se debe reintentar si se tiene respuesta del servicio. Si no hay disponibilidad del servicio se debe mostrar al cajero mediante un mensaje. | J24: Riesgo de duplicidad de transacciones si no se controla en backoffice. Riesgo de tiempo del cajero si el error persiste y no se identifica la no conexión con el servicio.
A25: Geo-Impresión del Documento como sustento de la transacción. | B25: Como negocio, quiero recibir un documento de recaudo propio del servicio, para tener respaldo de la operación realizada en Oxxo. | C25: Se debe generar un documento impreso con los datos de la operación. El documento debe ser legible y con las especificaciones permitidas para cada servicio. El documento debe servir como respaldo válido para un comprobante de pago de servicio La impresión del documento debe ser emitido por duplicado uno para cliente y el otro para el cajero. Los servicios estan exonerados de IGV. El documento nos es un comprobante tributario por lo cual no se debe emitir como factura o boleta de venta, ya que se define como comprobante de recaudo. | D25: MVP1 | E25: HU23- Restricción de devolución/extorno | F25: Como cajero, quiero que la aplicación no me permita realizar extornos o devoluciones una vez confirmado un pago, para garantizar el cumplimiento de la política de no devoluciones establecida por el recaudo. | G25: Una vez confirmado el pago, el sistema no debe habilitar ninguna opción de extorno o devolución en la interfaz del cajero. Si el cajero intenta realizar una devolución, el sistema debe mostrar un mensaje: “No es posible realizar devoluciones ni extornos una vez confirmado el pago.” En el backoffice, los pagos deben registrarse únicamente como operaciones definitivas, sin opción de reversa. | H25: La restricción de deviolución es para todos los recaudos de servicio. | I25: Ningún pago confirmado debe ser revertido por el sistema Cualquier reclamo debe gestionarse por el canal del proveedor o recaudo. | J25: Impacto con respecto a la satisfacción del cliente al tener un pago errado, puede generar incomodidad o molestia.
E26: HU24- Estructura de los comprobante de pago | F26: Como negocio, quiero generar comprobantes de pago con estructura definida, para garantizar información completa y uniforme al cliente. | G26: El comprobante debe contener Datos de la transacción, Identificación, Detalles del servicioque, Información de pago, etc . veriicar la hoja 2 del excel. El formato debe ser estandar o de acuerdo a los tipos de convenio para todos los recaudos. El comprobante debe estar disponible en físico. El comprobante debe tener información del medio de pago que realizó el pago del servicio. | H26: La información del pago es proporcionado en la API del servicio. | I26: Todos los pagos deben generar comprobante válido. Los comprobantes deben salir por duplicado uno para el cliente y otro para oxxo . Los comprobantes deben tener la estructura y campos establecida por OXXO y los datos enviados en la API | J26: Información incompleta puede generar reclamos del cliente.
E27: HU25 - Reimpresión del comprobante | F27: Como cajero, quiero reimprimir el comprobante de un recaudo de servicio para poder entregarlo al cliente en caso de pérdida o error de impresión. | G27: El sistema permite seleccionar una operación de recaudo de servicio y reimprimir el comprobante. La reimpresión debe contener los mismos datos del comprobante original, con la leyenda “Reimpresión” visible. No se genera un nuevo asiento contable ni registro adicional. La acción queda registrada en el log de auditoría (usuario, fecha, hora, motivo). Se valida que no se exceda el límite de reimpresiones configurado. | H27: La funcionalidad de reimpresión ya existe en GeoPos y solo se debe extender a los comprobantes de recaudo de servicio. El cajero tiene los permisos adecuados para ejecutar la reimpresión. La reimpresión no genera un nuevo asiento contable ni un nuevo registro en el módulo de servicios, solo reproduce el comprobante original. | I27: El comprobante a reimprimir debe corresponder exactamente a una transacción existente y válida en el sistema. El sistema debe marcar el comprobante como “Reimpreso”. El número de comprobante no cambia en la reimpresión. Se debe permitir un número limitado de reimpresiones por comprobante | J27: Uso indebido de la reimpresión Reimpresiones excesivas sin control
A28: EBS- Creación de tabla customizada | B28: Como negocio, quiero que se cree una tabla customizada y que Geo alimente esta tabla con la información de los servicios. | C28: Debe crearse una tabla customizada en EBS para replicar la información del servicio desde Geo. La tabla debe permitir la alimentación de la información de los servicios de forma automática, enviada desde Geo. Replicar la configuración del servicio en una tabla customizada que estará alojada en EBS. Tabla Custom en EBS Cabecera: RUT Proveedor, Nombre Proveedor, Código ITEM, Descripción, Código Impuesto, Tasa Impuesto, Costo, Precio de Venta, Comisión: Si-No, Tipo Comisión: Fija-Porcentaje, Valor Comisión, Afecta GL: Si-NO, Afecta AP: SI-NO, Afecta AR: SI - NO, Tipo Documento AP: Factura-Nota Crédito, Valor Documento AP: Total-Comisión, Tipo Documento AR: Factura - Nota de Crédito, Valor Documento AR: Total-Comisión, Descripción Asiento, frecuencia de facturación a AR y AP. Tabla Custom en EBS Líneas: Origen: Servicios, Código ITEM, No Línea, Tipo Afectación: Plaza-CR Tienda, Valor a Considerar: Costo-Precio de Venta, Tipo Movimiento: Debito-Crédito, Cuenta, Descripción Línea, frecuencia de facturación a AR y AP. | D28: MVP1 | E28: HU26 – Creación de tabla customizada en EBS | F28: Como negocio, quiero que se cree una tabla customizada en EBS y que GEO alimente automáticamente esta tabla con la información de los servicios configurados, para mantener sincronizada la información de “Recaudo de Servicios ”. | G28: Debe crearse una tabla customizada en EBS con los campos requeridos para replicar la configuración del servicio proveniente de GEO. GEO debe enviar automáticamente la información de los servicios configurados hacia esta tabla, sin intervención manual. Debe existir un mecanismo de integración o API que permita la transferencia segura y controlada de datos entre GEO y EBS. La información enviada desde GEO debe ser validada y registrada correctamente en la tabla EBS (confirmación de recepción y logs de integración). Debe garantizarse la trazabilidad de la información replicada (fecha de envío, usuario, servicio, ID del registro). La tabla debe permitir consultas y mantenimiento controlado (solo usuarios EBS autorizados). La estructura de la tabla debe soportar campos parametrizables (por ejemplo, moneda, tipo de fondeo, vigencia, tipo de servicio, comisiones, afectación contable, etc.); según archivo "Definiciones Carretera de Servicios 2" Los campos configurados en GEO que cambien (por ejemplo, cambio de estatus, monto, divisa) deben actualizarse automáticamente en la tabla customizada EBS. La integración debe manejar errores y reintentos automáticos en caso de falla de transmisión. | H28: GEO tiene definidos todos los campos de configuración del servicio, y los marcados con “*” son los únicos requeridos por EBS. La integración GEO /EBS utiliza un canal seguro previamente validado por el área técnica. Los identificadores clave como ID_Servicio y Código_Servicio son únicos y se utilizan como referencia en EBS. Las tablas de referencia (moneda, tipo de impuesto, estatus, etc.) ya existen en EBS. Los usuarios de EBS tienen permisos de solo lectura sobre la tabla customizada. La sincronización se ejecuta de forma automática y periódica (por ejemplo, diaria o según configuración). La tabla no reemplaza otras tablas EBS; solo sirve como fuente de réplica de datos provenientes de GEO. | I28: Solo se deben replicar servicios con estatus Activo en GEO. Cada registro replicado debe contener los campos indicados en el archivo "Definiciones Carretera de Servicios 2". Si un campo requerido para EBS no tiene valor en GEO, el sistema debe rechazar la replicación y registrar el error en log. Las actualizaciones de datos en GEO deben sobrescribir el registro existente en EBS, manteniendo histórico de cambios. Si un servicio cambia su estatus a “Inactivo”, deberá reflejarse igual en EBS (sin eliminar el registro). La estructura de la tabla debe permitir la trazabilidad entre los módulos contables de Cuentas por Pagar (AP) y Cuentas por Cobrar (AR). La tabla debe integrarse con las pólizas contables, utilizando los campos Origen_Póliza, Categoría_Póliza, Cuenta_Contable, DR/CR, Nivel. | J28: Riesgo de inconsistencia de datos si la integración entre GEO y EBS falla o no se validan los registros duplicados. Pérdida de trazabilidad si no se registran correctamente los logs de envío y actualización. Posible impacto en conciliaciones contables si se replica información errónea o incompleta. Riesgo de sobrecarga de tabla si no se depuran registros históricos. Dependencia técnica de la integración (si cambia estructura en GEO o EBS, puede romper el enlace). Riesgo de errores en auditoría si no se versionan correctamente los campos replicados.
A29: EBS-Generación de póliza contable | B29: Como negocio, quiero que se genere la poliza contable de los servicios emitidos para ser expuesta a GL_interface. | C29: El sistema debe generar una cuenta contable por los servicios emitidos. Las cuentas debe ser enviada a la GL_interface para la integración a EBS. La póliza consolidada debe ser por día, tienda y servicio. | D29: MVP1 | E29: HU27 – Generación de póliza por servicios | F29: Como negocio quiero que se genere la póliza contable de los servicios emitidos para que pueda ser expuesta a la GL_interface e integrada a EBS | G29: El sistema debe generar una cuenta contable por el servicio emitido. La póliza debe consolidarse por día, tienda y servicio. La información debe enviarse automáticamente a la GL_interface. | H29: Los servicios emitidos están validados en el POS. El catálogo contable de los servicios está previamente configurado en EBS. | I29: La póliza contable no podrá generarse sin la configuración previa del servicio en el catálogo contable. Una vez enviada a GL_interface, no se puede modificar, consultar como se revierte | J29: Error en la consolidación diaria puede generar duplicados Fallos de integración con GL_interface.
A30: EBS-Automatización de la importación de los servicios | B30: Como negocio, quiero que las polizas que lleguen como servicios se importen y contabilice en automático | C30: El proceso se debe dejar programado para ejecución una vez al día posterior a la hora de generación de importación del punto de venta. | D30: MVP1 | E30: HU28- Integración contable EBS | F30: Como negocio requiero que EBS tenga al día - 1 la información de los servicios en su contabilidad, mediante un proceso de importación y contabilización automática de servicios | G30: El proceso debe ejecutarse una vez al día, posterior a la hora de generación en POS. El sistema debe validar la integridad de la información antes de contabilizar. En caso de error, se debe generar un log con detalle. | H30: Geo genera las pólizas de servicios de manera consolidada y en un formato compatible con EBS. existe conectividad estable entre el Geo y EBS para la transferencia de información | I30: La importación solo se realiza una vez al día en el horario programado. El sistema debe validar la integridad antes de la contabilización. Las pólizas válidas deben contabilizarse automáticamente sin intervención manual. Que pasa si hay error | J30: Que no se genere la póliza en el horario esperado Inconsistencia en los datos Caída en la conectividad entre Geo y EBS durante la importación.
A31: EBS-Automatización de facturación en modulo de cuentas por pagar | B31: Como negocio, en caso que el servicio debe generar una factura en cuenta por pagar esta debe generarse con la configuración definida en el servicio. (Frecuencia y nivel de consolidación) | C31: La información Se va tomar de la información ya procesada en el módulo de contablidad y con la conf que tenga validado el servicio | D31: MVP1 | E31: HU29- Generación automatica de facturación de proveedor | F31: Como negocio requiero que si el Servicio tiene configurado que genera en AP una Factura/Nota de crédito esta se genere de manera automática con la información previamente procesada en GL y con base en la frecuencia de generación configurada, en GL se debe marcar la información ya considerada para evitar duplicar o tener faltantes en la Factura. | G31: La factura se genera con la frecuencia y consolidación definida en la configuración del servicio. La información proviene del módulo de contabilidad procesado. El sistema debe registrar la factura en cuentas por pagar (consultar con el estado) | H31: Los servicios tienen configurada la regla de facturación (frecuencia, nivel de consolidación, proveedor). La información contable ya está validada y disponible en el módulo. El sistema de cuentas por pagar tiene configurado los proveedores y condiciones de pago. La factura puede generarse por el Total de Recaudo, por el monto solo de la comisión o por el Total de Recaudo menos comisión, esto se debe definir como parte de la configuración del Servicio | I31: La factura en cuentas por pagar se genera automáticamente según la frecuencia definida (diaria, semanal, mensual). El nivel de consolidación debe ser de acuerdo a lo configurado en el servicio. | J31: Configuración incompleta o incorrecta del servicio. Diferencias entre la contabilidad y el módulo de cuentas por pagar genera rechaza. Errores en la parametrización o condiciones de pago.
A32: EBS-Automatización de facturación en modulo de cuentas por cobrar | B32: Como negocio, en caso que el servicio debe generar una factura en cuentas por cobrar esta debe generarse con la configuración definida en el servicio. (Frecuencia y nivel de consolidación) | C32: La información Se va tomar de la información ya procesada en el módulo de contablidad y con la conf que tenga validado el servicio | D32: MVP1 | E32: HU30- Generación automatica de facturación a clientes | F32: Como negocio requiero que si el Servicio tiene configurado que genera en AR una Factura/Nota de crédito esta se genere de manera automática con la información previamente procesada en GL y con base en la frecuencia de generación configurada, en GL se debe marcar la información ya considerada para evitar duplicar o tener faltantes en la Factura. | G32: La factura se genera con la frecuencia y consolidación definida en la configuración del servicio. La información proviene del módulo de contabilidad procesado. El sistema debe registrar la factura en cuentas por cobrar (consultar con el estado) | H32: Los servicios tienen configurada la regla de facturación (frecuencia, nivel de consolidación, proveedor). La información contable ya está validada y disponible en el módulo. El sistema de cuentas por cobrar tiene configurado los proveedores y condiciones de pago. La factura puede generarse por el Total de Recaudo, por el monto solo de la comisión o por el Total de Recaudo menos comisión, esto se debe definir como parte de la configuración del Servicio | I32: La factura a clientes se genera con la frecuencia y nivel de consolidación definido en la configuración del servicio. La información utilizada debe provenir exclusivamente del módulo contable procesado. La factura debe registrarse en cuentas por cobrar | J32: Configuración incompleta o incorrecta del servicio. Diferencias entre la contabilidad y el módulo de cuentas por pagar genera rechaza. Errores en la parametrización o condiciones de pago.
A33: BI- Reportería recaudo de Servicios | B33: Como negocio, quiero contar con la información diaria de los pagos de servicios para las conciliaciones | C33: El reporte debe mostrar la información detallada por cada tipo de servicio. Debe separar la comision que pago el cliente por el recaudo y la comisión pactada entre OXXO y BBVA. Debe mapearse las operaciones que estan afectas y no afectas a IGV | D33: MVP1 | E33: HU31-Reportería recaudo de servicios y conciliaciones | F33: Como negocio quiero contar con la información diaria de los pagos de servicios para realizar los reporte y conciliaciones necesarias. | G33: El reporte debe mostrar toda información detallada de los recaudos de servicios transaccionados y las comisiones que se presente. Se debe tener diferencia de campos de las comisión pagada por el cliente y comisión pactada entre OXXO y BBVA Debe diferenciar operaciones afectas y no afectas a IGV. El reporte debe estar disponible al día siguiente de la operación. Se debe tener el campo definido del detalle de la comisión +++Enviar la información del Pos | H33: Las comisiones están previamente registradas en el sistema. Existe trazabilidad entre POS, EBS y BI. | I33: El reporte de los servicios serán expuestos por Geo en forma automática hacia ODS y luego seguirá los procesos que se requiere para la reportería BI. Toda operación debe estar identificada con la afectación y no afectación de IGV. Debe estar separado el monto con la comisión del servicio. Debe mostrar la comisión pactada entre OXXO y BBVA | J33: Descuadres por errores de integración. Retrasos en la disponibilidad del reporte.

Sheet Hoja2
A1: Comprobante de pago
C2: OXXO -CADENA DE COMERCIO PERU | E2: OXXO -CADENA DE COMERCIO PERU
C3: DIRECCIÓN DE LA TIENDA OXXO DONDE PAGO | E3: RUC DE OXXO | G3: OXXO -CADENA DE COMERCIO PERU
C4: LIMA | E4: DIRECCIÓN PRINCIPAL OXXO | G4: RUC DE OXXO
E5: DIRECCIÓN DE LA TIENDA OXXO DONDE PAGO
E6: LIMA
C7: LOCAL: | E7: LOCAL | G7: DIRECCIÓN PRINCIPAL OXXO
C8: CAJERO: | E8: CAJERO | G8: LIMA
C9: CAJA: | E9: CAJA
C11: FECHA Y HORA | E11: FECHA Y HORA | F11: 45937 | G11: 0.62083333
C12: EMISOR, SERVICIO,ENTIDAD, EMPRESA(el campo name en la mensajería) | E12: EMISOR, SERVICIO,ENTIDAD, EMPRESA(el campo name en la mensajería) | F12: sedapal | G12: 35 caracteres (el servicio)
C13: TIPO DE SERVICIO (consultar la cantidad de caracteres) | E13: TIPO DE SERVICIO (consultar la cantidad de caracteres) | F13: servicio de Aguaa | G13: 35 caracteres (el nombre del convenio)
C14: N° de operación | E14: N° de operación | F14: 11111
C15: Código de usuario | E15: Código de usuario | F15: 234567
C16: Titular: (bill holder)/base de datos e interconectado ) | E16: Titular: (bill holder)/base de datos e interconectado ) | F16: Matias R.
C17: Doc. de pago (Validar la cantidad de caracteres) | E17: Doc. de pago (Validar la cantidad de caracteres) | F17: Concepto de pago | K17: n1 | M17: n2
C18: Vencimiento | E18: Vencimiento | I18: doc pago
C19: Importe: | E19: Importe: | I19: vencimiento | K19: 45868 | M19: 45899
C20: Mora: | E20: Mora: | I20: importe
C21: Comisión | E21: Comisión | I21: cargo fijo
C22: Importe Total: | E22: Importe Total: | I22: mora
C23: Medio de Pago: Confirmar los campos de redondeo y vuelto | E23: Medio de Pago: Confirmar los campos de redondeo y vuelto
C24: Se indica el pago con que se va realizar en caso de efectivo que se inidique el vuelto | E24: Se indica el pago con que se va realizar en caso de efectivo que se inidique el vuelto
E27: Interconectado | F27: 38 caracteres | G27: esto es el codigo identificador, lo restantes sería para el concepto de pago
E28: Base de batos | F28: 48 caracteres | G28: esto es el codigo identificador, lo restantes sería para el concepto de pago
E29: Data Entry | F29: 48 caracteres | G29: esto es el codigo identificador que es fijo de 11 caracteres, lo restantes sería para el concepto de pago 37 caracteres
G30: no incluye fecha e importe solo codigo del comprobante
G31: nombre (campo) es variable depende dle recaudo , lo definene los titulares del recaudo y no está dentro d elos cararcteres definidos.
A35: Campos de configuración
B37: Recaudo de Servicios en Tienda | C37: Campo | D37: Consideraciones | E37: Comentario | F37: Valor por default | G37: Se ocupa para EBS | H37: Requerido/Opcional
B38: Tipo de Servicio | C38: Cash in | H38: Requerido
C39: Cash out | H39: Requerido
C40: Monto límite transacción | H40: Requerido
A41: FRONT | B41: Tipo de Negociación | C41: Servicio Tercerizado (Recaudador) | H41: Requerido
C42: Servicio Directo Proveedor Servicio
C43: Tipo de servicio | D43: *Nacional (Domiciliado) *Extranjero (No Domiciliado)
B44: Configuración Servicio | C44: Nombre del Proveedor | G44: * | H44: Requerido, tomar de la configuración de EBS la Lista de Valores
C45: Rut del Proveedor | G45: * | H45: Requerido, tomar de la configuración de EBS la Lista de Valores
C46: Sucursal del Proveedor | G46: * | H46: Requerido, tomar de la configuración de EBS la Lista de Valores
C47: Rubro del Servicio | D47: * Empresas * Universidades * Clubs * Colegios | H47: Opcional
C48: ID_Servicio | G48: * | H48: Consecutivo POS
C49: Código Servicio | G49: * | H49: Requerido
C50: Descripción del Servicio | G50: * | H50: Requerido
C51: Tipo de Impuesto | D51: IGV Exo Ina | F51: Ina | G51: * | H51: Requerido
C52: Tasa de Impuesto | D52: * 0% * 18% | E52: Debe estar sujeto a ajuste de disminución o aunmento. debe ser editables. | F52: 0 | G52: * | H52: Requerido
C53: Estatus | D53: * Activo * Inactivo | F53: Activo | G53: * | H53: Requerido dependiente de las fechas de Vigencia
C54: Vigencia del Servicio | D54: Fecha de Inicio | G54: * | H54: Requerido
D55: Fecha Fin | G55: * | H55: Requerido
C56: Forma de Pago | D56: * Efectivo * Electrónico (Tarjeta debito y Crédito, Billetera electrónica, Cupón) * Mixto | E56: Efectivo máximo: 1800 | F56: Efectivo | H56: Requerido
C57: Divisa de Cobro | D57: * Soles * USD | E57: Debe ser configurables a cualquier moneda | F57: Soles | H57: Requerido por Default Soles
C58: Aplicabilidad | D58: * Nacional * Ciertas Tiendas | E58: Todas las Tiendas Seleccionar que Tiendas aplica | F58: Nacional | H58: Requerido
C59: Tipo de Fondeo del Servicio | D59: * Fondos propios * Fondos variables (proveedor/oxxo) * Crédito de Proveedor | E59: * Monto de Crédito | H59: Opcional
C60: Monto de fondeo | H60: Opcional
C61: Consideración del fondeo | D61: * Diaria * Semanal * Quincenal * Mensual | H61: Opcional
C62: Nivel del Fondeo | D62: * Tienda * Compañía | H62: Opcional
C63: Aceptar Sobre Giros | D63: * Si * No | H63: Opcional
C64: Monto de sobregiro | H64: Opcional
C65: Nivel de sobregiro | D65: * Tienda * Compañía | H65: Opcional
C66: Consideración del sobregiro | D66: * Diaria * Semanal * Quincenal * Mensual | H66: Opcional
C67: Divisa de Fondeo | D67: * Soles * USD | E67: Debe ser configurables a cualquier moneda | H67: Opcional
C68: Documento Requerido | D68: * Boleta Simple * Factura * Constancia de Pago * Nota de crédito * Nota de débito | F68: Constancia de Pago | H68: Requerido
C69: Envío de Recaudo Tienda | D69: * Consolidado Día Servicio * Consolidado Día Proveedor | F69: Consolidado Día Servicio | H69: Requerido por Default Día/Servicio
C70: Costo Negociado del Servicio | E70: ? | H70: Opcional
C71: Precio de Venta Negociado del Servicio | E71: ? | H71: Opcional
B72: Comisiones | C72: Aplica comisión al Proveedor | D72: * Si * No | F72: Si | G72: * | H72: Requerido
C73: Comisión de Pago al Proveedor | D73: * Fija * Variable | F73: Fija | G73: * | H73: Requerido solo sí el campo Aplica comisión esta en Sí, si está en no, no habilitar este campo
C74: Unidad de Medida de la Comisión Proveedor | D74: * % * Monto | F74: Monto | G74: * | H74: Requerido solo sí el campo Aplica comisión esta en Sí, si está en no, no habilitar este campo
C75: Cálculo de la Comisión Proveedor | D75: * Valor * Transacción * Consolidada | G75: * | H75: Requerido solo sí el campo Aplica comisión esta en Sí, si está en no, no habilitar este campo
C76: Valor de la Comisión Proveedor | G76: * | H76: Requerido solo sí el campo Aplica comisión esta en Sí, si está en no, no habilitar este campo
C77: Comisión de Pago Cliente | D77: * Si * No | F77: No | H77: Requerido
C78: Comisión de Cobro Cliente | D78: * Fija * Variable | H78: Requerido solo sí el campo Aplica comisión esta en Sí, si está en no, no habilitar este campo
C79: Unidad de Medida de la Comisión Cliente | D79: * % * Monto | H79: Requerido solo sí el campo Aplica comisión esta en Sí, si está en no, no habilitar este campo
C80: Cálculo de la Comisión Cliente | D80: * Valor * Transacción * Consolidada | H80: Requerido solo sí el campo Aplica comisión esta en Sí, si está en no, no habilitar este campo
C81: Valor de la Comisión Cliente | H81: Requerido solo sí el campo Aplica comisión esta en Sí, si está en no, no habilitar este campo
A82: Contable | B82: Consideraciones EBS | C82: Afecta Cuentas por Pagar | D82: * Sí * No | F82: No | G82: * | H82: Requerido
C83: Documento Cuentas por Pagar | D83: * Factura * Nota de Crédito * Ambos * No Aplica | G83: * | H83: Requerido solo sí el campo Afecta cuentas por pagar esta en Sí, si está en no, no habilitar este campo
C84: Montos del Documento por Pagar | D84: * Total del Recaudo * Total del Recaudo menos Comisión * Comisión | G84: * | H84: Requerido solo sí el campo Afecta cuentas por pagar esta en Sí, si está en no, no habilitar este campo
C85: Frecuencia de Facturación | D85: * Diaria * Semanal * Quincenal * Mensual | G85: * | H85: Requerido solo sí el campo Afecta cuentas por pagar esta en Sí, si está en no, no habilitar este campo
C86: Nivel Facturación | D86: * Tienda * Compañía | G86: * | H86: Requerido solo sí el campo Afecta cuentas por pagar esta en Sí, si está en no, no habilitar este campo
C87: Tipo de Facturación | D87: * Servicio * Proveedor (Todos los Servicios) | G87: * | H87: Requerido solo sí el campo Afecta cuentas por pagar esta en Sí, si está en no, no habilitar este campo
C88: Afecta Cuentas por Cobrar | D88: * Sí * No | F88: No | G88: * | H88: Requerido
C89: Documento Cuentas por Cobrar | D89: * Factura * Nota de Crédito * Ambos * No Aplica | G89: * | H89: Requerido solo sí el campo Afecta cuentas por pagar esta en Sí, si está en no, no habilitar este campo
C90: Frecuencia de Facturación | D90: * Diaria * Semanal * Quincenal * Mensual | G90: * | H90: Requerido solo sí el campo Afecta cuentas por pagar esta en Sí, si está en no, no habilitar este campo
C91: Nivel Facturación | D91: * Tienda * Compañía | G91: * | H91: Requerido solo sí el campo Afecta cuentas por pagar esta en Sí, si está en no, no habilitar este campo
C92: Tipo de Facturación | D92: * Servicio * Proveedor (Todos los Servicios) | G92: * | H92: Requerido solo sí el campo Afecta cuentas por pagar esta en Sí, si está en no, no habilitar este campo
C93: Montos del Documento por Cobrar | D93: * Total del Recaudo * Total del Recaudo menos Comisión * Comisión | G93: * | H93: Requerido solo sí el campo Afecta cuentas por pagar esta en Sí, si está en no, no habilitar este campo
B94: Cabecera Póliza | C94: Origen Póliza | D94: * Servicios | F94: Servicios | G94: * | H94: Requerido
C95: Categoría Póliza | D95: * Servicios | F95: Servicios | G95: * | H95: Requerido
C96: ID_Servicio | G96: * | H96: Tomar de configuración Inicial Servicio
C97: Código Servicio | G97: * | H97: Tomar de configuración Inicial Servicio
C98: Descripción del Servicio | G98: * | H98: Tomar de configuración Inicial Servicio
B99: Líneas Póliza | C99: Detalle | D99: Cuenta Contable | E99: Afectación | G99: Nivel | H99: Monto
C100: Nó. De Línea | D100: 12121101 | E100: DR/CR | G100: Tienda/Plaza | H100: Total Recaudo, Comisión, Total-Comisión, Impuesto
